<xilinx:hls_fe_msgs>
    <msg msg_groups="" msg_id="207-5292" msg_severity="WARNING" msg_loc="firmware/nnet_utils/nnet_helpers.h:285:99" msg_body="unused parameter 'keep'">
        <args ClangWarningOption="unused-parameter"/>
    </msg>
    <msg msg_groups="" msg_id="207-5292" msg_severity="WARNING" msg_loc="firmware/nnet_utils/nnet_function_stubs.h:14:36" msg_body="unused parameter 'data'">
        <args ClangWarningOption="unused-parameter"/>
    </msg>
    <msg msg_groups="" msg_id="207-5292" msg_severity="WARNING" msg_loc="firmware/nnet_utils/nnet_function_stubs.h:15:36" msg_body="unused parameter 'buffer'">
        <args ClangWarningOption="unused-parameter"/>
    </msg>
    <msg msg_groups="" msg_id="207-5292" msg_severity="WARNING" msg_loc="firmware/nnet_utils/nnet_function_stubs.h:16:44" msg_body="unused parameter 'partition'">
        <args ClangWarningOption="unused-parameter"/>
    </msg>
    <msg msg_groups="" msg_id="207-5292" msg_severity="WARNING" msg_loc="firmware/nnet_utils/nnet_function_stubs.h:24:24" msg_body="unused parameter 'data'">
        <args ClangWarningOption="unused-parameter"/>
    </msg>
    <msg msg_groups="" msg_id="207-5292" msg_severity="WARNING" msg_loc="firmware/nnet_utils/nnet_function_stubs.h:25:24" msg_body="unused parameter 'buffer'">
        <args ClangWarningOption="unused-parameter"/>
    </msg>
    <msg msg_groups="" msg_id="207-5292" msg_severity="WARNING" msg_loc="firmware/nnet_utils/nnet_function_stubs.h:26:32" msg_body="unused parameter 'partition'">
        <args ClangWarningOption="unused-parameter"/>
    </msg>
    <msg msg_groups="" msg_id="207-5292" msg_severity="WARNING" msg_loc="firmware/nnet_utils/nnet_function_stubs.h:33:30" msg_body="unused parameter 'data'">
        <args ClangWarningOption="unused-parameter"/>
    </msg>
    <msg msg_groups="" msg_id="207-5292" msg_severity="WARNING" msg_loc="firmware/nnet_utils/nnet_function_stubs.h:33:58" msg_body="unused parameter 'res'">
        <args ClangWarningOption="unused-parameter"/>
    </msg>
    <msg msg_groups="" msg_id="207-5292" msg_severity="WARNING" msg_loc="firmware/nnet_utils/nnet_function_stubs.h:34:51" msg_body="unused parameter 'weights'">
        <args ClangWarningOption="unused-parameter"/>
    </msg>
    <msg msg_groups="" msg_id="207-5292" msg_severity="WARNING" msg_loc="firmware/nnet_utils/nnet_function_stubs.h:35:49" msg_body="unused parameter 'biases'">
        <args ClangWarningOption="unused-parameter"/>
    </msg>
    <msg msg_groups="" msg_id="207-5292" msg_severity="WARNING" msg_loc="firmware/nnet_utils/nnet_function_stubs.h:42:29" msg_body="unused parameter 'data'">
        <args ClangWarningOption="unused-parameter"/>
    </msg>
    <msg msg_groups="" msg_id="207-5292" msg_severity="WARNING" msg_loc="firmware/nnet_utils/nnet_function_stubs.h:42:80" msg_body="unused parameter 'res'">
        <args ClangWarningOption="unused-parameter"/>
    </msg>
    <msg msg_groups="" msg_id="207-5292" msg_severity="WARNING" msg_loc="firmware/nnet_utils/nnet_function_stubs.h:43:50" msg_body="unused parameter 'weights'">
        <args ClangWarningOption="unused-parameter"/>
    </msg>
    <msg msg_groups="" msg_id="207-5292" msg_severity="WARNING" msg_loc="firmware/nnet_utils/nnet_function_stubs.h:44:48" msg_body="unused parameter 'biases'">
        <args ClangWarningOption="unused-parameter"/>
    </msg>
    <msg msg_groups="" msg_id="207-5292" msg_severity="WARNING" msg_loc="firmware/nnet_utils/nnet_code_gen.h:16:39" msg_body="unused parameter 'data'">
        <args ClangWarningOption="unused-parameter"/>
    </msg>
    <msg msg_groups="" msg_id="207-5292" msg_severity="WARNING" msg_loc="firmware/nnet_utils/nnet_code_gen.h:17:38" msg_body="unused parameter 'res'">
        <args ClangWarningOption="unused-parameter"/>
    </msg>
    <msg msg_groups="" msg_id="207-5292" msg_severity="WARNING" msg_loc="firmware/nnet_utils/nnet_code_gen.h:18:60" msg_body="unused parameter 'weights'">
        <args ClangWarningOption="unused-parameter"/>
    </msg>
    <msg msg_groups="" msg_id="207-5292" msg_severity="WARNING" msg_loc="firmware/nnet_utils/nnet_code_gen.h:19:58" msg_body="unused parameter 'biases'">
        <args ClangWarningOption="unused-parameter"/>
    </msg>
    <msg msg_groups="PRAGMA_VERBOSE_DUMP" msg_id="207-5471" msg_severity="WARNING" msg_loc="firmware/nnet_utils/nnet_types.h:28:9" msg_body="HLS pragma dump">
        <args ARG_PragmaFunction="operator=" ARG_PragmaIsValid="1" ARG_PragmaType="unroll" ClangWarningOption="dump-hls-pragmas"/>
    </msg>
    <msg msg_groups="PRAGMA_VERBOSE_DUMP" msg_id="207-5471" msg_severity="WARNING" msg_loc="firmware/nnet_utils/nnet_mult.h:25:9" msg_body="HLS pragma dump">
        <args ARG_PragmaFunction="product" ARG_PragmaIsValid="1" ARG_PragmaType="inline" ClangWarningOption="dump-hls-pragmas"/>
    </msg>
    <msg msg_groups="PRAGMA_VERBOSE_DUMP" msg_id="207-5471" msg_severity="WARNING" msg_loc="firmware/nnet_utils/nnet_mult.h:34:9" msg_body="HLS pragma dump">
        <args ARG_PragmaFunction="product" ARG_PragmaIsValid="1" ARG_PragmaType="inline" ClangWarningOption="dump-hls-pragmas"/>
    </msg>
    <msg msg_groups="PRAGMA_VERBOSE_DUMP" msg_id="207-5471" msg_severity="WARNING" msg_loc="firmware/nnet_utils/nnet_mult.h:46:9" msg_body="HLS pragma dump">
        <args ARG_PragmaFunction="product" ARG_PragmaIsValid="1" ARG_PragmaType="inline" ClangWarningOption="dump-hls-pragmas"/>
    </msg>
    <msg msg_groups="PRAGMA_VERBOSE_DUMP" msg_id="207-5471" msg_severity="WARNING" msg_loc="firmware/nnet_utils/nnet_mult.h:58:9" msg_body="HLS pragma dump">
        <args ARG_PragmaFunction="product" ARG_PragmaIsValid="1" ARG_PragmaType="inline" ClangWarningOption="dump-hls-pragmas"/>
    </msg>
    <msg msg_groups="PRAGMA_VERBOSE_DUMP" msg_id="207-5471" msg_severity="WARNING" msg_loc="firmware/nnet_utils/nnet_mult.h:72:9" msg_body="HLS pragma dump">
        <args ARG_PragmaFunction="product" ARG_PragmaIsValid="1" ARG_PragmaType="inline" ClangWarningOption="dump-hls-pragmas"/>
    </msg>
    <msg msg_groups="PRAGMA_VERBOSE_DUMP" msg_id="207-5471" msg_severity="WARNING" msg_loc="firmware/nnet_utils/nnet_mult.h:82:9" msg_body="HLS pragma dump">
        <args ARG_PragmaFunction="product" ARG_PragmaIsValid="1" ARG_PragmaType="inline" ClangWarningOption="dump-hls-pragmas"/>
    </msg>
    <msg msg_groups="PRAGMA_VERBOSE_DUMP" msg_id="207-5471" msg_severity="WARNING" msg_loc="firmware/nnet_utils/nnet_conv1d_latency.h:19:9" msg_body="HLS pragma dump">
        <args ARG_PragmaFunction="conv_1d_latency_cl" ARG_PragmaIsValid="1" ARG_PragmaOptions="variable=data_buf complete dim=0" ARG_PragmaType="array_partition" ClangWarningOption="dump-hls-pragmas"/>
    </msg>
    <msg msg_groups="PRAGMA_VERBOSE_DUMP" msg_id="207-5471" msg_severity="WARNING" msg_loc="firmware/nnet_utils/nnet_conv1d_latency.h:22:9" msg_body="HLS pragma dump">
        <args ARG_PragmaFunction="conv_1d_latency_cl" ARG_PragmaIsValid="1" ARG_PragmaOptions="variable=mult complete" ARG_PragmaType="array_partition" ClangWarningOption="dump-hls-pragmas"/>
    </msg>
    <msg msg_groups="PRAGMA_VERBOSE_DUMP" msg_id="207-5471" msg_severity="WARNING" msg_loc="firmware/nnet_utils/nnet_conv1d_latency.h:25:9" msg_body="HLS pragma dump">
        <args ARG_PragmaFunction="conv_1d_latency_cl" ARG_PragmaIsValid="1" ARG_PragmaOptions="variable=acc complete" ARG_PragmaType="array_partition" ClangWarningOption="dump-hls-pragmas"/>
    </msg>
    <msg msg_groups="PRAGMA_VERBOSE_DUMP" msg_id="207-5471" msg_severity="WARNING" msg_loc="firmware/nnet_utils/nnet_conv1d_latency.h:27:9" msg_body="HLS pragma dump">
        <args ARG_PragmaFunction="conv_1d_latency_cl" ARG_PragmaIsValid="1" ARG_PragmaOptions="variable=weights complete" ARG_PragmaType="array_partition" ClangWarningOption="dump-hls-pragmas"/>
    </msg>
    <msg msg_groups="PRAGMA_VERBOSE_DUMP" msg_id="207-5471" msg_severity="WARNING" msg_loc="firmware/nnet_utils/nnet_conv1d_latency.h:28:9" msg_body="HLS pragma dump">
        <args ARG_PragmaFunction="conv_1d_latency_cl" ARG_PragmaIsValid="1" ARG_PragmaOptions="variable=biases complete" ARG_PragmaType="array_partition" ClangWarningOption="dump-hls-pragmas"/>
    </msg>
    <msg msg_groups="PRAGMA_VERBOSE_DUMP" msg_id="207-5471" msg_severity="WARNING" msg_loc="firmware/nnet_utils/nnet_conv1d_latency.h:31:9" msg_body="HLS pragma dump">
        <args ARG_PragmaFunction="conv_1d_latency_cl" ARG_PragmaIsValid="1" ARG_PragmaOptions="operation instances=mul limit=CONFIG_T::mult_config::multiplier_limit" ARG_PragmaType="allocation" ClangWarningOption="dump-hls-pragmas"/>
    </msg>
    <msg msg_groups="PRAGMA_VERBOSE_DUMP" msg_id="207-5471" msg_severity="WARNING" msg_loc="firmware/nnet_utils/nnet_conv1d_latency.h:35:9" msg_body="HLS pragma dump">
        <args ARG_PragmaFunction="conv_1d_latency_cl" ARG_PragmaIsValid="1" ARG_PragmaOptions="II=CONFIG_T::reuse_factor rewind" ARG_PragmaType="pipeline" ClangWarningOption="dump-hls-pragmas"/>
    </msg>
    <msg msg_groups="PRAGMA_VERBOSE_DUMP" msg_id="207-5471" msg_severity="WARNING" msg_loc="firmware/nnet_utils/nnet_conv1d_latency.h:41:9" msg_body="HLS pragma dump">
        <args ARG_PragmaFunction="conv_1d_latency_cl" ARG_PragmaIsValid="1" ARG_PragmaType="unroll" ClangWarningOption="dump-hls-pragmas"/>
    </msg>
    <msg msg_groups="PRAGMA_VERBOSE_DUMP" msg_id="207-5471" msg_severity="WARNING" msg_loc="firmware/nnet_utils/nnet_conv1d_latency.h:48:9" msg_body="HLS pragma dump">
        <args ARG_PragmaFunction="conv_1d_latency_cl" ARG_PragmaIsValid="1" ARG_PragmaType="unroll" ClangWarningOption="dump-hls-pragmas"/>
    </msg>
    <msg msg_groups="PRAGMA_VERBOSE_DUMP" msg_id="207-5471" msg_severity="WARNING" msg_loc="firmware/nnet_utils/nnet_conv1d_latency.h:52:9" msg_body="HLS pragma dump">
        <args ARG_PragmaFunction="conv_1d_latency_cl" ARG_PragmaIsValid="1" ARG_PragmaType="unroll" ClangWarningOption="dump-hls-pragmas"/>
    </msg>
    <msg msg_groups="PRAGMA_VERBOSE_DUMP" msg_id="207-5471" msg_severity="WARNING" msg_loc="firmware/nnet_utils/nnet_conv1d_latency.h:62:9" msg_body="HLS pragma dump">
        <args ARG_PragmaFunction="conv_1d_latency_cl" ARG_PragmaIsValid="1" ARG_PragmaType="unroll" ClangWarningOption="dump-hls-pragmas"/>
    </msg>
    <msg msg_groups="PRAGMA_VERBOSE_DUMP" msg_id="207-5471" msg_severity="WARNING" msg_loc="firmware/nnet_utils/nnet_conv1d_latency.h:69:9" msg_body="HLS pragma dump">
        <args ARG_PragmaFunction="conv_1d_latency_cl" ARG_PragmaIsValid="1" ARG_PragmaType="unroll" ClangWarningOption="dump-hls-pragmas"/>
    </msg>
    <msg msg_groups="PRAGMA_VERBOSE_DUMP" msg_id="207-5471" msg_severity="WARNING" msg_loc="firmware/nnet_utils/nnet_conv1d_latency.h:72:9" msg_body="HLS pragma dump">
        <args ARG_PragmaFunction="conv_1d_latency_cl" ARG_PragmaIsValid="1" ARG_PragmaType="unroll" ClangWarningOption="dump-hls-pragmas"/>
    </msg>
    <msg msg_groups="PRAGMA_VERBOSE_DUMP" msg_id="207-5471" msg_severity="WARNING" msg_loc="firmware/nnet_utils/nnet_conv1d_latency.h:80:9" msg_body="HLS pragma dump">
        <args ARG_PragmaFunction="conv_1d_latency_cl" ARG_PragmaIsValid="1" ARG_PragmaType="unroll" ClangWarningOption="dump-hls-pragmas"/>
    </msg>
    <msg msg_groups="PRAGMA_VERBOSE_DUMP" msg_id="207-5471" msg_severity="WARNING" msg_loc="firmware/nnet_utils/nnet_conv1d_latency.h:97:9" msg_body="HLS pragma dump">
        <args ARG_PragmaFunction="pointwise_conv_1d_latency_cl" ARG_PragmaIsValid="1" ARG_PragmaOptions="variable=mult complete dim=0" ARG_PragmaType="array_partition" ClangWarningOption="dump-hls-pragmas"/>
    </msg>
    <msg msg_groups="PRAGMA_VERBOSE_DUMP" msg_id="207-5471" msg_severity="WARNING" msg_loc="firmware/nnet_utils/nnet_conv1d_latency.h:98:9" msg_body="HLS pragma dump">
        <args ARG_PragmaFunction="pointwise_conv_1d_latency_cl" ARG_PragmaIsValid="1" ARG_PragmaOptions="variable=acc complete dim=0" ARG_PragmaType="array_partition" ClangWarningOption="dump-hls-pragmas"/>
    </msg>
    <msg msg_groups="PRAGMA_VERBOSE_DUMP" msg_id="207-5471" msg_severity="WARNING" msg_loc="firmware/nnet_utils/nnet_conv1d_latency.h:101:9" msg_body="HLS pragma dump">
        <args ARG_PragmaFunction="pointwise_conv_1d_latency_cl" ARG_PragmaIsValid="1" ARG_PragmaOptions="variable=weights,biases" ARG_PragmaType="function_instantiate" ClangWarningOption="dump-hls-pragmas"/>
    </msg>
    <msg msg_groups="PRAGMA_VERBOSE_DUMP" msg_id="207-5471" msg_severity="WARNING" msg_loc="firmware/nnet_utils/nnet_conv1d_latency.h:104:9" msg_body="HLS pragma dump">
        <args ARG_PragmaFunction="pointwise_conv_1d_latency_cl" ARG_PragmaIsValid="1" ARG_PragmaOptions="II=CONFIG_T::reuse_factor" ARG_PragmaType="pipeline" ClangWarningOption="dump-hls-pragmas"/>
    </msg>
    <msg msg_groups="PRAGMA_VERBOSE_DUMP" msg_id="207-5471" msg_severity="WARNING" msg_loc="firmware/nnet_utils/nnet_conv1d_latency.h:105:9" msg_body="HLS pragma dump">
        <args ARG_PragmaFunction="pointwise_conv_1d_latency_cl" ARG_PragmaIsValid="1" ARG_PragmaOptions="variable=weights complete dim=0" ARG_PragmaType="array_partition" ClangWarningOption="dump-hls-pragmas"/>
    </msg>
    <msg msg_groups="PRAGMA_VERBOSE_DUMP" msg_id="207-5471" msg_severity="WARNING" msg_loc="firmware/nnet_utils/nnet_conv1d_latency.h:106:9" msg_body="HLS pragma dump">
        <args ARG_PragmaFunction="pointwise_conv_1d_latency_cl" ARG_PragmaIsValid="1" ARG_PragmaOptions="variable=biases complete dim=0" ARG_PragmaType="array_partition" ClangWarningOption="dump-hls-pragmas"/>
    </msg>
    <msg msg_groups="PRAGMA_VERBOSE_DUMP" msg_id="207-5471" msg_severity="WARNING" msg_loc="firmware/nnet_utils/nnet_conv1d_latency.h:109:9" msg_body="HLS pragma dump">
        <args ARG_PragmaFunction="pointwise_conv_1d_latency_cl" ARG_PragmaIsValid="1" ARG_PragmaOptions="operation instances=mul limit=CONFIG_T::mult_config::multiplier_limit" ARG_PragmaType="allocation" ClangWarningOption="dump-hls-pragmas"/>
    </msg>
    <msg msg_groups="PRAGMA_VERBOSE_DUMP" msg_id="207-5471" msg_severity="WARNING" msg_loc="firmware/nnet_utils/nnet_conv1d_latency.h:118:9" msg_body="HLS pragma dump">
        <args ARG_PragmaFunction="pointwise_conv_1d_latency_cl" ARG_PragmaIsValid="1" ARG_PragmaType="unroll" ClangWarningOption="dump-hls-pragmas"/>
    </msg>
    <msg msg_groups="PRAGMA_VERBOSE_DUMP" msg_id="207-5471" msg_severity="WARNING" msg_loc="firmware/nnet_utils/nnet_conv1d_latency.h:137:9" msg_body="HLS pragma dump">
        <args ARG_PragmaFunction="pointwise_conv_1d_latency_cl" ARG_PragmaIsValid="1" ARG_PragmaType="unroll" ClangWarningOption="dump-hls-pragmas"/>
    </msg>
    <msg msg_groups="PRAGMA_VERBOSE_DUMP" msg_id="207-5471" msg_severity="WARNING" msg_loc="firmware/nnet_utils/nnet_conv1d_latency.h:159:9" msg_body="HLS pragma dump">
        <args ARG_PragmaFunction="pointwise_conv_1d_latency_cl" ARG_PragmaIsValid="1" ARG_PragmaType="unroll" ClangWarningOption="dump-hls-pragmas"/>
    </msg>
    <msg msg_groups="PRAGMA_VERBOSE_DUMP" msg_id="207-5471" msg_severity="WARNING" msg_loc="/data/hlssynt-users/rflynn/transformer-synthesis/hls4ml_projects/keras_mha_Vitis/build_prj.tcl:183:9" msg_body="HLS pragma dump">
        <args ARG_PragmaContext="directive" ARG_PragmaFunction="myproject" ARG_PragmaIsValid="1" ARG_PragmaOptions="name=myproject" ARG_PragmaType="top" ClangWarningOption="dump-hls-pragmas"/>
    </msg>
    <msg msg_groups="PRAGMA_VERBOSE_DUMP" msg_id="207-5471" msg_severity="WARNING" msg_loc="firmware/myproject.cpp:13:9" msg_body="HLS pragma dump">
        <args ARG_PragmaFunction="myproject" ARG_PragmaIsValid="1" ARG_PragmaOptions="variable=input_1 complete dim=0" ARG_PragmaType="array_reshape" ClangWarningOption="dump-hls-pragmas"/>
    </msg>
    <msg msg_groups="PRAGMA_VERBOSE_DUMP" msg_id="207-5471" msg_severity="WARNING" msg_loc="firmware/myproject.cpp:14:9" msg_body="HLS pragma dump">
        <args ARG_PragmaFunction="myproject" ARG_PragmaIsValid="1" ARG_PragmaOptions="variable=input_2 complete dim=0" ARG_PragmaType="array_reshape" ClangWarningOption="dump-hls-pragmas"/>
    </msg>
    <msg msg_groups="PRAGMA_VERBOSE_DUMP" msg_id="207-5471" msg_severity="WARNING" msg_loc="firmware/myproject.cpp:15:9" msg_body="HLS pragma dump">
        <args ARG_PragmaFunction="myproject" ARG_PragmaIsValid="1" ARG_PragmaOptions="variable=layer3_out complete dim=0" ARG_PragmaType="array_partition" ClangWarningOption="dump-hls-pragmas"/>
    </msg>
    <msg msg_groups="PRAGMA_VERBOSE_DUMP" msg_id="207-5471" msg_severity="WARNING" msg_loc="firmware/myproject.cpp:16:9" msg_body="HLS pragma dump">
        <args ARG_PragmaFunction="myproject" ARG_PragmaIsValid="1" ARG_PragmaOptions="ap_vld port=input_1,input_2,layer3_out" ARG_PragmaType="interface" ClangWarningOption="dump-hls-pragmas"/>
    </msg>
    <msg msg_groups="PRAGMA_VERBOSE_DUMP" msg_id="207-5471" msg_severity="WARNING" msg_loc="firmware/myproject.cpp:17:9" msg_body="HLS pragma dump">
        <args ARG_PragmaFunction="myproject" ARG_PragmaIsValid="1" ARG_PragmaType="pipeline" ClangWarningOption="dump-hls-pragmas"/>
    </msg>
    <msg msg_groups="PRAGMA_ARRAY_PARTITION" msg_id="214-180" msg_severity="WARNING" msg_loc="firmware/myproject.cpp:15:9" msg_body="The array partition pragma on function argument, in 'call' is unsupported">
        <args Pragma="call" Pragma-DebugLoc="File firmware/myproject.cpp Line 15 Column 9"/>
    </msg>
    <msg msg_groups="PRAGMA_INTERFACE" msg_id="214-313" msg_severity="ERROR" msg_loc="firmware/myproject.cpp:10:0" msg_body="Unsupport interface pragma on struct type with opaque, argument 'layer3_out' of function 'myproject(ap_fixed&lt;16, 6, (ap_q_mode)5, (ap_o_mode)3, 0&gt;*, ap_fixed&lt;16, 6, (ap_q_mode)5, (ap_o_mode)3, 0&gt;*, ap_fixed&lt;33, 13, (ap_q_mode)5, (ap_o_mode)3, 0&gt;*)'">
        <args Argument="layer3_out" Function="myproject(ap_fixed&lt;16, 6, (ap_q_mode)5, (ap_o_mode)3, 0&gt;*, ap_fixed&lt;16, 6, (ap_q_mode)5, (ap_o_mode)3, 0&gt;*, ap_fixed&lt;33, 13, (ap_q_mode)5, (ap_o_mode)3, 0&gt;*)" Function-DebugLoc="File firmware/myproject.cpp Line 10 Column 0"/>
    </msg>
</xilinx:hls_fe_msgs>

