<pragmas>
<pragma file="" line="0" pragmaType="inline" parentfunction="ap_fixed<22, 6, (ap_q_mode)5, (ap_o_mode)3, 0>::ap_fixed(double)" off="0" region="0" recursive="0"/>
<pragma file="" line="0" pragmaType="inline" parentfunction="ap_fixed<22, 6, (ap_q_mode)5, (ap_o_mode)3, 0>::ap_fixed<16, 6, true, (ap_q_mode)5, (ap_o_mode)3, 0>(ap_fixed_base<16, 6, true, (ap_q_mode)5, (ap_o_mode)3, 0> const&)" off="0" region="0" recursive="0"/>
<pragma file="" line="0" pragmaType="inline" parentfunction="ap_fixed_base<33, 13, true, (ap_q_mode)5, (ap_o_mode)3, 0>& ap_fixed_base<33, 13, true, (ap_q_mode)5, (ap_o_mode)3, 0>::operator=<60, 20, true, (ap_q_mode)5, (ap_o_mode)3, 0>(ap_fixed_base<60, 20, true, (ap_q_mode)5, (ap_o_mode)3, 0> const&)" off="0" region="0" recursive="0"/>
<pragma file="firmware/nnet_utils/nnet_mult.h" line="72" pragmaType="inline" parentfunction="product" off="0" region="0" recursive="0"/>
<pragma file="" line="0" pragmaType="inline" parentfunction="ap_int_base<13, true>::ap_int_base<11, false>(ap_int_base<11, false> const&)" off="0" region="0" recursive="0"/>
<pragma file="" line="0" pragmaType="inline" parentfunction="ap_int_base<13, true>::ap_int_base<12, true>(ap_int_base<12, true> const&)" off="0" region="0" recursive="0"/>
<pragma file="" line="0" pragmaType="inline" parentfunction="ap_int_base<13, true>::ap_int_base(int)" off="0" region="0" recursive="0"/>
<pragma file="" line="0" pragmaType="inline" parentfunction="ap_fixed<21, 7, (ap_q_mode)5, (ap_o_mode)3, 0>::ap_fixed(int)" off="0" region="0" recursive="0"/>
<pragma file="" line="0" pragmaType="inline" parentfunction="ap_fixed<22, 6, (ap_q_mode)5, (ap_o_mode)3, 0>::ap_fixed(int)" off="0" region="0" recursive="0"/>
<pragma file="" line="0" pragmaType="inline" parentfunction="ap_int_base<11, false>::RType<12, true>::minus operator-<11, false, 12, true>(ap_int_base<11, false> const&, ap_int_base<12, true> const&)" off="0" region="0" recursive="0"/>
<pragma file="" line="0" pragmaType="inline" parentfunction="ap_fixed<16, 6, (ap_q_mode)5, (ap_o_mode)3, 0>::ap_fixed(double)" off="0" region="0" recursive="0"/>
<pragma file="/opt/Xilinx/Vitis_HLS/2023.2/common/technology/autopilot/etc/ap_common.h" line="515" pragmaType="inline" parentfunction="_ZN8ssdm_intILi55ELb1EEC2EDq55_i" off="0" region="0" recursive="0"/>
<pragma file="" line="0" pragmaType="inline" parentfunction="ap_int_base<55, true>::ap_int_base(int)" off="0" region="0" recursive="0"/>
<pragma file="/opt/Xilinx/Vitis_HLS/2023.2/common/technology/autopilot/etc/ap_common.h" line="523" pragmaType="inline" parentfunction="_ZN8ssdm_intILi1ELb0EEC2EDq1_j" off="0" region="0" recursive="0"/>
<pragma file="" line="0" pragmaType="inline" parentfunction="ap_int_base<54, true>& ap_int_base<54, true>::operator=<55, true>(ap_int_base<55, true> const&)" off="0" region="0" recursive="0"/>
<pragma file="" line="0" pragmaType="inline" parentfunction="ap_int<55>::ap_int<55, true>(ap_int_base<55, true> const&)" off="0" region="0" recursive="0"/>
<pragma file="/opt/Xilinx/Vitis_HLS/2023.2/common/technology/autopilot/etc/ap_common.h" line="718" pragmaType="inline" parentfunction="doubleToRawBits" off="0" region="0" recursive="0"/>
<pragma file="" line="0" pragmaType="inline" parentfunction="ap_int_base<12, true>::ap_int_base(int)" off="0" region="0" recursive="0"/>
<pragma file="" line="0" pragmaType="inline" parentfunction="ap_int<13>::ap_int<13, true>(ap_int_base<13, true> const&)" off="0" region="0" recursive="0"/>
<pragma file="/opt/Xilinx/Vitis_HLS/2023.2/common/technology/autopilot/etc/ap_common.h" line="515" pragmaType="inline" parentfunction="_ZN8ssdm_intILi13ELb1EEC2EDq13_i" off="0" region="0" recursive="0"/>
<pragma file="/opt/Xilinx/Vitis_HLS/2023.2/common/technology/autopilot/etc/ap_common.h" line="515" pragmaType="inline" parentfunction="_ZN8ssdm_intILi12ELb1EEC2EDq12_i" off="0" region="0" recursive="0"/>
<pragma file="firmware/myproject.cpp" line="16" pragmaType="pipeline" parentfunction="myproject" off="0" ii="-1" style=""/>
<pragma file="firmware/myproject.cpp" line="13" pragmaType="array_reshape" parentfunction="myproject" dim="0" factor="0" mode="complete" variable="layer_normalization_input"/>
<pragma file="firmware/myproject.cpp" line="14" pragmaType="array_partition" parentfunction="myproject" dim="0" factor="0" mode="complete" dynamic="0" variable="layer2_out"/>
<pragma file="firmware/myproject.cpp" line="15" pragmaType="interface" parentfunction="myproject" mode="ap_vld" port="layer2_out" name="" register="0"/>
<pragma file="firmware/myproject.cpp" line="15" pragmaType="interface" parentfunction="myproject" mode="ap_vld" port="layer_normalization_input" name="" register="0"/>
<pragma file="" line="0" pragmaType="inline" parentfunction="ap_int_base<1, false>::ap_int_base(int)" off="0" region="0" recursive="0"/>
<pragma file="" line="0" pragmaType="inline" parentfunction="ap_int_base<1, false>::RType<54, true>::minus operator-<1, false, 54, true>(ap_int_base<1, false> const&, ap_int_base<54, true> const&)" off="0" region="0" recursive="0"/>
<pragma file="" line="0" pragmaType="inline" parentfunction="ap_int_base<55, true>::ap_int_base<1, false>(ap_int_base<1, false> const&)" off="0" region="0" recursive="0"/>
<pragma file="" line="0" pragmaType="inline" parentfunction="ap_int_base<55, true>::ap_int_base<54, true>(ap_int_base<54, true> const&)" off="0" region="0" recursive="0"/>
<pragma file="" line="0" pragmaType="inline" parentfunction="ap_int_base<54, true>::operator-() const" off="0" region="0" recursive="0"/>
<pragma file="" line="0" pragmaType="inline" parentfunction="report" off="0" region="0" recursive="0"/>
<pragma file="" line="0" pragmaType="inline" parentfunction="ap_fixed<22, 6, (ap_q_mode)5, (ap_o_mode)3, 0>::ap_fixed<44, 12, true, (ap_q_mode)5, (ap_o_mode)3, 0>(ap_fixed_base<44, 12, true, (ap_q_mode)5, (ap_o_mode)3, 0> const&)" off="0" region="0" recursive="0"/>
<pragma file="" line="0" pragmaType="inline" parentfunction="ap_fixed_base<22, 6, true, (ap_q_mode)5, (ap_o_mode)3, 0>::RType<22, 6, true>::minus ap_fixed_base<22, 6, true, (ap_q_mode)5, (ap_o_mode)3, 0>::operator-<22, 6, true, (ap_q_mode)5, (ap_o_mode)3, 0>(ap_fixed_base<22, 6, true, (ap_q_mode)5, (ap_o_mode)3, 0> const&) const" off="0" region="0" recursive="0"/>
<pragma file="" line="0" pragmaType="inline" parentfunction="ap_fixed<22, 6, (ap_q_mode)5, (ap_o_mode)3, 0>::ap_fixed<23, 7, true, (ap_q_mode)5, (ap_o_mode)3, 0>(ap_fixed_base<23, 7, true, (ap_q_mode)5, (ap_o_mode)3, 0> const&)" off="0" region="0" recursive="0"/>
<pragma file="" line="0" pragmaType="inline" parentfunction="ap_fixed_base<22, 6, true, (ap_q_mode)5, (ap_o_mode)3, 0>::RType<22, 6, true>::mult ap_fixed_base<22, 6, true, (ap_q_mode)5, (ap_o_mode)3, 0>::operator*<22, 6, true, (ap_q_mode)5, (ap_o_mode)3, 0>(ap_fixed_base<22, 6, true, (ap_q_mode)5, (ap_o_mode)3, 0> const&) const" off="0" region="0" recursive="0"/>
<pragma file="" line="0" pragmaType="inline" parentfunction="ap_fixed_base<22, 6, true, (ap_q_mode)5, (ap_o_mode)3, 0>::RType<22, 6, true>::plus ap_fixed_base<22, 6, true, (ap_q_mode)5, (ap_o_mode)3, 0>::operator+<22, 6, true, (ap_q_mode)5, (ap_o_mode)3, 0>(ap_fixed_base<22, 6, true, (ap_q_mode)5, (ap_o_mode)3, 0> const&) const" off="0" region="0" recursive="0"/>
<pragma file="firmware/nnet_utils/nnet_layernorm.h" line="74" pragmaType="pipeline" parentfunction="lookup_invert_sqr" off="0" ii="-1" style=""/>
<pragma file="firmware/nnet_utils/nnet_layernorm.h" line="77" pragmaType="unroll" parentfunction="lookup_invert_sqr" factor="4" skip_exit_check="0"/>
<pragma file="" line="0" pragmaType="inline" parentfunction="ap_fixed_base<22, 6, true, (ap_q_mode)5, (ap_o_mode)3, 0>::RType<21, 7, true>::mult ap_fixed_base<22, 6, true, (ap_q_mode)5, (ap_o_mode)3, 0>::operator*<21, 7, true, (ap_q_mode)5, (ap_o_mode)3, 0>(ap_fixed_base<21, 7, true, (ap_q_mode)5, (ap_o_mode)3, 0> const&) const" off="0" region="0" recursive="0"/>
<pragma file="" line="0" pragmaType="inline" parentfunction="ap_fixed_base<43, 13, true, (ap_q_mode)5, (ap_o_mode)3, 0>::RType<16, 6, true>::mult ap_fixed_base<43, 13, true, (ap_q_mode)5, (ap_o_mode)3, 0>::operator*<16, 6, true, (ap_q_mode)5, (ap_o_mode)3, 0>(ap_fixed_base<16, 6, true, (ap_q_mode)5, (ap_o_mode)3, 0> const&) const" off="0" region="0" recursive="0"/>
<pragma file="" line="0" pragmaType="inline" parentfunction="ap_fixed_base<59, 19, true, (ap_q_mode)5, (ap_o_mode)3, 0>::RType<16, 6, true>::plus ap_fixed_base<59, 19, true, (ap_q_mode)5, (ap_o_mode)3, 0>::operator+<16, 6, true, (ap_q_mode)5, (ap_o_mode)3, 0>(ap_fixed_base<16, 6, true, (ap_q_mode)5, (ap_o_mode)3, 0> const&) const" off="0" region="0" recursive="0"/>
<pragma file="" line="0" pragmaType="inline" parentfunction="ap_fixed<33, 13, (ap_q_mode)5, (ap_o_mode)3, 0>::ap_fixed<60, 20, true, (ap_q_mode)5, (ap_o_mode)3, 0>(ap_fixed_base<60, 20, true, (ap_q_mode)5, (ap_o_mode)3, 0> const&)" off="0" region="0" recursive="0"/>
<pragma file="" line="0" pragmaType="inline" parentfunction="ap_fixed_base<33, 13, true, (ap_q_mode)5, (ap_o_mode)3, 0>::ap_fixed_base<60, 20, true, (ap_q_mode)5, (ap_o_mode)3, 0>(ap_fixed_base<60, 20, true, (ap_q_mode)5, (ap_o_mode)3, 0> const&)" off="0" region="0" recursive="0"/>
<pragma file="/opt/Xilinx/Vitis_HLS/2023.2/common/technology/autopilot/etc/ap_common.h" line="515" pragmaType="inline" parentfunction="_ZN8ssdm_intILi33ELb1EEC2EDq33_i" off="0" region="0" recursive="0"/>
<pragma file="" line="0" pragmaType="inline" parentfunction="report" off="0" region="0" recursive="0"/>
<pragma file="" line="0" pragmaType="inline" parentfunction="ap_fixed_base<60, 20, true, (ap_q_mode)5, (ap_o_mode)3, 0>::operator!() const" off="0" region="0" recursive="0"/>
<pragma file="" line="0" pragmaType="inline" parentfunction="ap_fixed_base<60, 20, true, (ap_q_mode)5, (ap_o_mode)3, 0>::ap_fixed_base(int)" off="0" region="0" recursive="0"/>
<pragma file="" line="0" pragmaType="inline" parentfunction="ap_fixed_base<60, 20, true, (ap_q_mode)5, (ap_o_mode)3, 0>::ap_fixed_base<59, 19, true, (ap_q_mode)5, (ap_o_mode)3, 0>(ap_fixed_base<59, 19, true, (ap_q_mode)5, (ap_o_mode)3, 0> const&)" off="0" region="0" recursive="0"/>
<pragma file="" line="0" pragmaType="inline" parentfunction="ap_fixed_base<60, 20, true, (ap_q_mode)5, (ap_o_mode)3, 0>::ap_fixed_base<16, 6, true, (ap_q_mode)5, (ap_o_mode)3, 0>(ap_fixed_base<16, 6, true, (ap_q_mode)5, (ap_o_mode)3, 0> const&)" off="0" region="0" recursive="0"/>
<pragma file="" line="0" pragmaType="inline" parentfunction="ap_fixed<60, 20, (ap_q_mode)5, (ap_o_mode)3, 0>::ap_fixed<60, 20, true, (ap_q_mode)5, (ap_o_mode)3, 0>(ap_fixed_base<60, 20, true, (ap_q_mode)5, (ap_o_mode)3, 0> const&)" off="0" region="0" recursive="0"/>
<pragma file="/opt/Xilinx/Vitis_HLS/2023.2/common/technology/autopilot/etc/ap_common.h" line="515" pragmaType="inline" parentfunction="_ZN8ssdm_intILi60ELb1EEC2EDq60_i" off="0" region="0" recursive="0"/>
<pragma file="" line="0" pragmaType="inline" parentfunction="report" off="0" region="0" recursive="0"/>
<pragma file="" line="0" pragmaType="inline" parentfunction="ap_fixed_base<16, 6, true, (ap_q_mode)5, (ap_o_mode)3, 0>::operator!() const" off="0" region="0" recursive="0"/>
<pragma file="" line="0" pragmaType="inline" parentfunction="ap_fixed_base<60, 20, true, (ap_q_mode)5, (ap_o_mode)3, 0>& ap_fixed_base<60, 20, true, (ap_q_mode)5, (ap_o_mode)3, 0>::operator=<32, 32, true, (ap_q_mode)5, (ap_o_mode)3, 0>(ap_fixed_base<32, 32, true, (ap_q_mode)5, (ap_o_mode)3, 0> const&)" off="0" region="0" recursive="0"/>
<pragma file="" line="0" pragmaType="inline" parentfunction="ap_fixed_base<59, 19, true, (ap_q_mode)5, (ap_o_mode)3, 0>::operator!() const" off="0" region="0" recursive="0"/>
<pragma file="" line="0" pragmaType="inline" parentfunction="ap_fixed_base<59, 19, true, (ap_q_mode)5, (ap_o_mode)3, 0>& ap_fixed_base<59, 19, true, (ap_q_mode)5, (ap_o_mode)3, 0>::operator=<32, 32, true, (ap_q_mode)5, (ap_o_mode)3, 0>(ap_fixed_base<32, 32, true, (ap_q_mode)5, (ap_o_mode)3, 0> const&)" off="0" region="0" recursive="0"/>
<pragma file="" line="0" pragmaType="inline" parentfunction="ap_fixed_base<32, 32, true, (ap_q_mode)5, (ap_o_mode)3, 0>::operator!() const" off="0" region="0" recursive="0"/>
<pragma file="" line="0" pragmaType="inline" parentfunction="ap_fixed_base<59, 19, true, (ap_q_mode)5, (ap_o_mode)3, 0>::ap_fixed_base(int)" off="0" region="0" recursive="0"/>
<pragma file="" line="0" pragmaType="inline" parentfunction="ap_fixed<59, 19, (ap_q_mode)5, (ap_o_mode)3, 0>::ap_fixed<59, 19, true, (ap_q_mode)5, (ap_o_mode)3, 0>(ap_fixed_base<59, 19, true, (ap_q_mode)5, (ap_o_mode)3, 0> const&)" off="0" region="0" recursive="0"/>
<pragma file="" line="0" pragmaType="inline" parentfunction="ap_fixed_base<43, 13, true, (ap_q_mode)5, (ap_o_mode)3, 0>& ap_fixed_base<43, 13, true, (ap_q_mode)5, (ap_o_mode)3, 0>::operator=<32, 32, true, (ap_q_mode)5, (ap_o_mode)3, 0>(ap_fixed_base<32, 32, true, (ap_q_mode)5, (ap_o_mode)3, 0> const&)" off="0" region="0" recursive="0"/>
<pragma file="" line="0" pragmaType="inline" parentfunction="ap_fixed_base<43, 13, true, (ap_q_mode)5, (ap_o_mode)3, 0>::ap_fixed_base(int)" off="0" region="0" recursive="0"/>
<pragma file="" line="0" pragmaType="inline" parentfunction="ap_fixed<43, 13, (ap_q_mode)5, (ap_o_mode)3, 0>::ap_fixed<43, 13, true, (ap_q_mode)5, (ap_o_mode)3, 0>(ap_fixed_base<43, 13, true, (ap_q_mode)5, (ap_o_mode)3, 0> const&)" off="0" region="0" recursive="0"/>
<pragma file="" line="0" pragmaType="inline" parentfunction="ap_fixed_base<23, 7, true, (ap_q_mode)5, (ap_o_mode)3, 0>& ap_fixed_base<23, 7, true, (ap_q_mode)5, (ap_o_mode)3, 0>::operator=<21, 7, true, (ap_q_mode)5, (ap_o_mode)3, 0>(ap_fixed_base<21, 7, true, (ap_q_mode)5, (ap_o_mode)3, 0> const&)" off="0" region="0" recursive="0"/>
<pragma file="" line="0" pragmaType="inline" parentfunction="bool ap_fixed_base<22, 6, true, (ap_q_mode)5, (ap_o_mode)3, 0>::operator<=<21, 7, true, (ap_q_mode)5, (ap_o_mode)3, 0>(ap_fixed_base<21, 7, true, (ap_q_mode)5, (ap_o_mode)3, 0> const&) const" off="0" region="0" recursive="0"/>
<pragma file="" line="0" pragmaType="inline" parentfunction="bool ap_fixed_base<22, 6, true, (ap_q_mode)5, (ap_o_mode)3, 0>::operator>=<21, 7, true, (ap_q_mode)5, (ap_o_mode)3, 0>(ap_fixed_base<21, 7, true, (ap_q_mode)5, (ap_o_mode)3, 0> const&) const" off="0" region="0" recursive="0"/>
<pragma file="" line="0" pragmaType="inline" parentfunction="ap_fixed_base<23, 7, true, (ap_q_mode)5, (ap_o_mode)3, 0>::ap_fixed_base<21, 7, true, (ap_q_mode)5, (ap_o_mode)3, 0>(ap_fixed_base<21, 7, true, (ap_q_mode)5, (ap_o_mode)3, 0> const&)" off="0" region="0" recursive="0"/>
<pragma file="/opt/Xilinx/Vitis_HLS/2023.2/common/technology/autopilot/etc/ap_common.h" line="515" pragmaType="inline" parentfunction="_ZN8ssdm_intILi23ELb1EEC2EDq23_i" off="0" region="0" recursive="0"/>
<pragma file="" line="0" pragmaType="inline" parentfunction="report" off="0" region="0" recursive="0"/>
<pragma file="" line="0" pragmaType="inline" parentfunction="ap_fixed_base<21, 7, true, (ap_q_mode)5, (ap_o_mode)3, 0>::operator!() const" off="0" region="0" recursive="0"/>
<pragma file="" line="0" pragmaType="inline" parentfunction="ap_fixed_base<23, 7, true, (ap_q_mode)5, (ap_o_mode)3, 0>::ap_fixed_base(int)" off="0" region="0" recursive="0"/>
<pragma file="" line="0" pragmaType="inline" parentfunction="ap_fixed_base<23, 7, true, (ap_q_mode)5, (ap_o_mode)3, 0>::ap_fixed_base<22, 6, true, (ap_q_mode)5, (ap_o_mode)3, 0>(ap_fixed_base<22, 6, true, (ap_q_mode)5, (ap_o_mode)3, 0> const&)" off="0" region="0" recursive="0"/>
<pragma file="" line="0" pragmaType="inline" parentfunction="ap_fixed<23, 7, (ap_q_mode)5, (ap_o_mode)3, 0>::ap_fixed<23, 7, true, (ap_q_mode)5, (ap_o_mode)3, 0>(ap_fixed_base<23, 7, true, (ap_q_mode)5, (ap_o_mode)3, 0> const&)" off="0" region="0" recursive="0"/>
<pragma file="" line="0" pragmaType="inline" parentfunction="ap_fixed_base<23, 7, true, (ap_q_mode)5, (ap_o_mode)3, 0>& ap_fixed_base<23, 7, true, (ap_q_mode)5, (ap_o_mode)3, 0>::operator=<32, 32, true, (ap_q_mode)5, (ap_o_mode)3, 0>(ap_fixed_base<32, 32, true, (ap_q_mode)5, (ap_o_mode)3, 0> const&)" off="0" region="0" recursive="0"/>
<pragma file="" line="0" pragmaType="inline" parentfunction="ap_fixed_base<22, 6, true, (ap_q_mode)5, (ap_o_mode)3, 0>::operator!() const" off="0" region="0" recursive="0"/>
<pragma file="" line="0" pragmaType="inline" parentfunction="ap_fixed_base<44, 12, true, (ap_q_mode)5, (ap_o_mode)3, 0>& ap_fixed_base<44, 12, true, (ap_q_mode)5, (ap_o_mode)3, 0>::operator=<32, 32, true, (ap_q_mode)5, (ap_o_mode)3, 0>(ap_fixed_base<32, 32, true, (ap_q_mode)5, (ap_o_mode)3, 0> const&)" off="0" region="0" recursive="0"/>
<pragma file="" line="0" pragmaType="inline" parentfunction="ap_fixed_base<22, 6, true, (ap_q_mode)5, (ap_o_mode)3, 0>::ap_fixed_base<23, 7, true, (ap_q_mode)5, (ap_o_mode)3, 0>(ap_fixed_base<23, 7, true, (ap_q_mode)5, (ap_o_mode)3, 0> const&)" off="0" region="0" recursive="0"/>
<pragma file="" line="0" pragmaType="inline" parentfunction="ap_fixed_base<44, 12, true, (ap_q_mode)5, (ap_o_mode)3, 0>::ap_fixed_base(int)" off="0" region="0" recursive="0"/>
<pragma file="" line="0" pragmaType="inline" parentfunction="ap_fixed<44, 12, (ap_q_mode)5, (ap_o_mode)3, 0>::ap_fixed<44, 12, true, (ap_q_mode)5, (ap_o_mode)3, 0>(ap_fixed_base<44, 12, true, (ap_q_mode)5, (ap_o_mode)3, 0> const&)" off="0" region="0" recursive="0"/>
<pragma file="" line="0" pragmaType="inline" parentfunction="ap_fixed_base<22, 6, true, (ap_q_mode)5, (ap_o_mode)3, 0>& ap_fixed_base<22, 6, true, (ap_q_mode)5, (ap_o_mode)3, 0>::operator=<23, 7, true, (ap_q_mode)5, (ap_o_mode)3, 0>(ap_fixed_base<23, 7, true, (ap_q_mode)5, (ap_o_mode)3, 0> const&)" off="0" region="0" recursive="0"/>
<pragma file="/opt/Xilinx/Vitis_HLS/2023.2/common/technology/autopilot/etc/ap_common.h" line="515" pragmaType="inline" parentfunction="_ZN8ssdm_intILi22ELb1EEC2EDq22_i" off="0" region="0" recursive="0"/>
<pragma file="" line="0" pragmaType="inline" parentfunction="report" off="0" region="0" recursive="0"/>
<pragma file="" line="0" pragmaType="inline" parentfunction="ap_fixed_base<23, 7, true, (ap_q_mode)5, (ap_o_mode)3, 0>::operator!() const" off="0" region="0" recursive="0"/>
<pragma file="" line="0" pragmaType="inline" parentfunction="ap_fixed_base<22, 6, true, (ap_q_mode)5, (ap_o_mode)3, 0>::ap_fixed_base<44, 12, true, (ap_q_mode)5, (ap_o_mode)3, 0>(ap_fixed_base<44, 12, true, (ap_q_mode)5, (ap_o_mode)3, 0> const&)" off="0" region="0" recursive="0"/>
<pragma file="" line="0" pragmaType="inline" parentfunction="ap_fixed_base<22, 6, true, (ap_q_mode)5, (ap_o_mode)3, 0>& ap_fixed_base<22, 6, true, (ap_q_mode)5, (ap_o_mode)3, 0>::operator=<16, 6, true, (ap_q_mode)5, (ap_o_mode)3, 0>(ap_fixed_base<16, 6, true, (ap_q_mode)5, (ap_o_mode)3, 0> const&)" off="0" region="0" recursive="0"/>
<pragma file="" line="0" pragmaType="inline" parentfunction="ap_fixed_base<44, 12, true, (ap_q_mode)5, (ap_o_mode)3, 0>::operator!() const" off="0" region="0" recursive="0"/>
<pragma file="" line="0" pragmaType="inline" parentfunction="ap_fixed_base<22, 6, true, (ap_q_mode)5, (ap_o_mode)3, 0>::ap_fixed_base<16, 6, true, (ap_q_mode)5, (ap_o_mode)3, 0>(ap_fixed_base<16, 6, true, (ap_q_mode)5, (ap_o_mode)3, 0> const&)" off="0" region="0" recursive="0"/>
<pragma file="" line="0" pragmaType="inline" parentfunction="ap_fixed_base<22, 6, true, (ap_q_mode)5, (ap_o_mode)3, 0>& ap_fixed_base<22, 6, true, (ap_q_mode)5, (ap_o_mode)3, 0>::operator=<32, 32, true, (ap_q_mode)5, (ap_o_mode)3, 0>(ap_fixed_base<32, 32, true, (ap_q_mode)5, (ap_o_mode)3, 0> const&)" off="0" region="0" recursive="0"/>
<pragma file="" line="0" pragmaType="inline" parentfunction="ap_fixed_base<22, 6, true, (ap_q_mode)5, (ap_o_mode)3, 0>::ap_fixed_base(int)" off="0" region="0" recursive="0"/>
<pragma file="" line="0" pragmaType="inline" parentfunction="report" off="0" region="0" recursive="0"/>
<pragma file="" line="0" pragmaType="inline" parentfunction="ap_fixed<21, 7, (ap_q_mode)5, (ap_o_mode)3, 0>::ap_fixed(float)" off="0" region="0" recursive="0"/>
<pragma file="" line="0" pragmaType="inline" parentfunction="ap_fixed<21, 7, (ap_q_mode)5, (ap_o_mode)3, 0>::ap_fixed(double)" off="0" region="0" recursive="0"/>
<pragma file="" line="0" pragmaType="inline" parentfunction="ap_fixed_base<21, 7, true, (ap_q_mode)5, (ap_o_mode)3, 0>::ap_fixed_base(float)" off="0" region="0" recursive="0"/>
<pragma file="" line="0" pragmaType="inline" parentfunction="ap_fixed_base<21, 7, true, (ap_q_mode)5, (ap_o_mode)3, 0>::ap_fixed_base(int)" off="0" region="0" recursive="0"/>
<pragma file="firmware/nnet_utils/nnet_layernorm.h" line="170" pragmaType="pipeline" parentfunction="layernormalize" off="0" ii="-1" rewind="0" style=""/>
<pragma file="firmware/nnet_utils/nnet_layernorm.h" line="173" pragmaType="unroll" parentfunction="layernormalize" factor="-1" skip_exit_check="0"/>
<pragma file="firmware/nnet_utils/nnet_layernorm.h" line="179" pragmaType="unroll" parentfunction="layernormalize" factor="-1" skip_exit_check="0"/>
<pragma file="firmware/nnet_utils/nnet_layernorm.h" line="161" pragmaType="function_instantiate" parentfunction="layernormalize" variable="bias"/>
<pragma file="firmware/nnet_utils/nnet_layernorm.h" line="161" pragmaType="function_instantiate" parentfunction="layernormalize" variable="scale"/>
<pragma file="firmware/nnet_utils/nnet_layernorm.h" line="163" pragmaType="array_partition" parentfunction="layernormalize" dim="1" factor="0" mode="complete" dynamic="0" variable="scale"/>
<pragma file="firmware/nnet_utils/nnet_layernorm.h" line="164" pragmaType="array_partition" parentfunction="layernormalize" dim="1" factor="0" mode="complete" dynamic="0" variable="bias"/>
<pragma file="firmware/nnet_utils/nnet_layernorm.h" line="165" pragmaType="array_partition" parentfunction="layernormalize" dim="1" factor="0" mode="complete" dynamic="0" variable="in_val"/>
<pragma file="firmware/nnet_utils/nnet_layernorm.h" line="166" pragmaType="array_partition" parentfunction="layernormalize" dim="1" factor="0" mode="complete" dynamic="0" variable="outval"/>
<pragma file="firmware/nnet_utils/nnet_layernorm.h" line="92" pragmaType="pipeline" parentfunction="layernorm_1d" off="0" ii="1" style=""/>
<pragma file="firmware/nnet_utils/nnet_layernorm.h" line="93" pragmaType="array_partition" parentfunction="layernorm_1d" dim="1" factor="0" mode="complete" dynamic="0" variable="data"/>
<pragma file="firmware/nnet_utils/nnet_layernorm.h" line="94" pragmaType="array_partition" parentfunction="layernorm_1d" dim="1" factor="0" mode="complete" dynamic="0" variable="res"/>
<pragma file="firmware/nnet_utils/nnet_layernorm.h" line="122" pragmaType="array_partition" parentfunction="layernorm_1d" dim="1" factor="0" mode="complete" dynamic="0" variable="data_diff"/>
<pragma file="" line="0" pragmaType="inline" parentfunction="ap_fixed_base<22, 6, true, (ap_q_mode)5, (ap_o_mode)3, 0>& ap_fixed_base<22, 6, true, (ap_q_mode)5, (ap_o_mode)3, 0>::operator+=<22, 6, true, (ap_q_mode)5, (ap_o_mode)3, 0>(ap_fixed_base<22, 6, true, (ap_q_mode)5, (ap_o_mode)3, 0> const&)" off="0" region="0" recursive="0"/>
<pragma file="" line="0" pragmaType="inline" parentfunction="ap_fixed_base<60, 20, true, (ap_q_mode)5, (ap_o_mode)3, 0>& ap_fixed_base<60, 20, true, (ap_q_mode)5, (ap_o_mode)3, 0>::operator=<16, 6, true, (ap_q_mode)5, (ap_o_mode)3, 0>(ap_fixed_base<16, 6, true, (ap_q_mode)5, (ap_o_mode)3, 0> const&)" off="0" region="0" recursive="0"/>
<pragma file="" line="0" pragmaType="inline" parentfunction="ap_fixed_base<60, 20, true, (ap_q_mode)5, (ap_o_mode)3, 0>& ap_fixed_base<60, 20, true, (ap_q_mode)5, (ap_o_mode)3, 0>::operator=<59, 19, true, (ap_q_mode)5, (ap_o_mode)3, 0>(ap_fixed_base<59, 19, true, (ap_q_mode)5, (ap_o_mode)3, 0> const&)" off="0" region="0" recursive="0"/>
<pragma file="" line="0" pragmaType="inline" parentfunction="ap_int_base<12, true>& ap_int_base<12, true>::operator=<13, true>(ap_int_base<13, true> const&)" off="0" region="0" recursive="0"/>
<pragma file="" line="0" pragmaType="inline" parentfunction="ap_fixed_base<23, 7, true, (ap_q_mode)5, (ap_o_mode)3, 0>& ap_fixed_base<23, 7, true, (ap_q_mode)5, (ap_o_mode)3, 0>::operator=<22, 6, true, (ap_q_mode)5, (ap_o_mode)3, 0>(ap_fixed_base<22, 6, true, (ap_q_mode)5, (ap_o_mode)3, 0> const&)" off="0" region="0" recursive="0"/>
<pragma file="" line="0" pragmaType="inline" parentfunction="ap_fixed_base<22, 6, true, (ap_q_mode)5, (ap_o_mode)3, 0>& ap_fixed_base<22, 6, true, (ap_q_mode)5, (ap_o_mode)3, 0>::operator=<44, 12, true, (ap_q_mode)5, (ap_o_mode)3, 0>(ap_fixed_base<44, 12, true, (ap_q_mode)5, (ap_o_mode)3, 0> const&)" off="0" region="0" recursive="0"/>
<pragma file="" line="0" pragmaType="inline" parentfunction="ap_fixed_base<21, 7, true, (ap_q_mode)5, (ap_o_mode)3, 0>& ap_fixed_base<21, 7, true, (ap_q_mode)5, (ap_o_mode)3, 0>::operator=<32, 32, true, (ap_q_mode)5, (ap_o_mode)3, 0>(ap_fixed_base<32, 32, true, (ap_q_mode)5, (ap_o_mode)3, 0> const&)" off="0" region="0" recursive="0"/>
</pragmas>
