<profile>

<ReportVersion>
<Version>2023.2</Version>
</ReportVersion>

<UserAssignments>
<unit>ns</unit>
<ProductFamily>virtexuplus</ProductFamily>
<Part>xcvu13p-flga2577-2-e</Part>
<TopModelName>layernormalize_ap_fixed_16_6_5_3_0_ap_fixed_33_13_5_3_0_config2_s</TopModelName>
<TargetClockPeriod>5.00</TargetClockPeriod>
<ClockUncertainty>0.62</ClockUncertainty>
<TargetInitiationInterval>4294967295</TargetInitiationInterval>
<FlowTarget>vivado</FlowTarget>
</UserAssignments>

<PerformanceEstimates>
<PipelineType>yes</PipelineType>
<SummaryOfTimingAnalysis>
<unit>ns</unit>
<EstimatedClockPeriod>4.097</EstimatedClockPeriod>
</SummaryOfTimingAnalysis>
<SummaryOfOverallLatency>
<unit>clock cycles</unit>
<Best-caseLatency>3</Best-caseLatency>
<Average-caseLatency>3</Average-caseLatency>
<Worst-caseLatency>3</Worst-caseLatency>
<Best-caseRealTimeLatency>15.000 ns</Best-caseRealTimeLatency>
<Average-caseRealTimeLatency>15.000 ns</Average-caseRealTimeLatency>
<Worst-caseRealTimeLatency>15.000 ns</Worst-caseRealTimeLatency>
<PipelineInitiationInterval>1</PipelineInitiationInterval>
<PipelineDepth>4</PipelineDepth>
<Interval-min>1</Interval-min>
<Interval-max>1</Interval-max>
</SummaryOfOverallLatency>
<SummaryOfViolations>
<IssueType>-</IssueType>
<ViolationType>-</ViolationType>
<SourceLocation>firmware/nnet_utils/nnet_layernorm.h:124</SourceLocation>
</SummaryOfViolations>
</PerformanceEstimates>

<AreaEstimates>
<Resources>
<BRAM_18K>40</BRAM_18K>
<DSP>160</DSP>
<FF>7254</FF>
<LUT>9822</LUT>
<URAM>0</URAM>
</Resources>
<AvailableResources>
<BRAM_18K>5376</BRAM_18K>
<DSP>12288</DSP>
<FF>3456000</FF>
<LUT>1728000</LUT>
<URAM>1280</URAM>
</AvailableResources>
</AreaEstimates>

<InterfaceSummary>
<RtlPorts>
<name>ap_clk</name>
<Object>layernormalize&lt;ap_fixed&lt;16, 6, 5, 3, 0&gt;, ap_fixed&lt;33, 13, 5, 3, 0&gt;, config2&gt;</Object>
<Type>return value</Type>
<Scope></Scope>
<IOProtocol>ap_ctrl_hs</IOProtocol>
<IOConfig></IOConfig>
<Dir>in</Dir>
<Bits>1</Bits>
<Attribute>control</Attribute>
</RtlPorts>
<RtlPorts>
<name>ap_rst</name>
<Object>layernormalize&lt;ap_fixed&lt;16, 6, 5, 3, 0&gt;, ap_fixed&lt;33, 13, 5, 3, 0&gt;, config2&gt;</Object>
<Type>return value</Type>
<Scope></Scope>
<IOProtocol>ap_ctrl_hs</IOProtocol>
<IOConfig></IOConfig>
<Dir>in</Dir>
<Bits>1</Bits>
<Attribute>control</Attribute>
</RtlPorts>
<RtlPorts>
<name>ap_start</name>
<Object>layernormalize&lt;ap_fixed&lt;16, 6, 5, 3, 0&gt;, ap_fixed&lt;33, 13, 5, 3, 0&gt;, config2&gt;</Object>
<Type>return value</Type>
<Scope></Scope>
<IOProtocol>ap_ctrl_hs</IOProtocol>
<IOConfig></IOConfig>
<Dir>in</Dir>
<Bits>1</Bits>
<Attribute>control</Attribute>
</RtlPorts>
<RtlPorts>
<name>ap_done</name>
<Object>layernormalize&lt;ap_fixed&lt;16, 6, 5, 3, 0&gt;, ap_fixed&lt;33, 13, 5, 3, 0&gt;, config2&gt;</Object>
<Type>return value</Type>
<Scope></Scope>
<IOProtocol>ap_ctrl_hs</IOProtocol>
<IOConfig></IOConfig>
<Dir>out</Dir>
<Bits>1</Bits>
<Attribute>control</Attribute>
</RtlPorts>
<RtlPorts>
<name>ap_idle</name>
<Object>layernormalize&lt;ap_fixed&lt;16, 6, 5, 3, 0&gt;, ap_fixed&lt;33, 13, 5, 3, 0&gt;, config2&gt;</Object>
<Type>return value</Type>
<Scope></Scope>
<IOProtocol>ap_ctrl_hs</IOProtocol>
<IOConfig></IOConfig>
<Dir>out</Dir>
<Bits>1</Bits>
<Attribute>control</Attribute>
</RtlPorts>
<RtlPorts>
<name>ap_ready</name>
<Object>layernormalize&lt;ap_fixed&lt;16, 6, 5, 3, 0&gt;, ap_fixed&lt;33, 13, 5, 3, 0&gt;, config2&gt;</Object>
<Type>return value</Type>
<Scope></Scope>
<IOProtocol>ap_ctrl_hs</IOProtocol>
<IOConfig></IOConfig>
<Dir>out</Dir>
<Bits>1</Bits>
<Attribute>control</Attribute>
</RtlPorts>
<RtlPorts>
<name>ap_ce</name>
<Object>layernormalize&lt;ap_fixed&lt;16, 6, 5, 3, 0&gt;, ap_fixed&lt;33, 13, 5, 3, 0&gt;, config2&gt;</Object>
<Type>return value</Type>
<Scope></Scope>
<IOProtocol>ap_ctrl_hs</IOProtocol>
<IOConfig></IOConfig>
<Dir>in</Dir>
<Bits>1</Bits>
<Attribute>control</Attribute>
</RtlPorts>
<RtlPorts>
<name>ap_return_0</name>
<Object>layernormalize&lt;ap_fixed&lt;16, 6, 5, 3, 0&gt;, ap_fixed&lt;33, 13, 5, 3, 0&gt;, config2&gt;</Object>
<Type>return value</Type>
<Scope></Scope>
<IOProtocol>ap_ctrl_hs</IOProtocol>
<IOConfig></IOConfig>
<Dir>out</Dir>
<Bits>33</Bits>
<Attribute>data</Attribute>
</RtlPorts>
<RtlPorts>
<name>ap_return_1</name>
<Object>layernormalize&lt;ap_fixed&lt;16, 6, 5, 3, 0&gt;, ap_fixed&lt;33, 13, 5, 3, 0&gt;, config2&gt;</Object>
<Type>return value</Type>
<Scope></Scope>
<IOProtocol>ap_ctrl_hs</IOProtocol>
<IOConfig></IOConfig>
<Dir>out</Dir>
<Bits>33</Bits>
<Attribute>data</Attribute>
</RtlPorts>
<RtlPorts>
<name>ap_return_2</name>
<Object>layernormalize&lt;ap_fixed&lt;16, 6, 5, 3, 0&gt;, ap_fixed&lt;33, 13, 5, 3, 0&gt;, config2&gt;</Object>
<Type>return value</Type>
<Scope></Scope>
<IOProtocol>ap_ctrl_hs</IOProtocol>
<IOConfig></IOConfig>
<Dir>out</Dir>
<Bits>33</Bits>
<Attribute>data</Attribute>
</RtlPorts>
<RtlPorts>
<name>ap_return_3</name>
<Object>layernormalize&lt;ap_fixed&lt;16, 6, 5, 3, 0&gt;, ap_fixed&lt;33, 13, 5, 3, 0&gt;, config2&gt;</Object>
<Type>return value</Type>
<Scope></Scope>
<IOProtocol>ap_ctrl_hs</IOProtocol>
<IOConfig></IOConfig>
<Dir>out</Dir>
<Bits>33</Bits>
<Attribute>data</Attribute>
</RtlPorts>
<RtlPorts>
<name>ap_return_4</name>
<Object>layernormalize&lt;ap_fixed&lt;16, 6, 5, 3, 0&gt;, ap_fixed&lt;33, 13, 5, 3, 0&gt;, config2&gt;</Object>
<Type>return value</Type>
<Scope></Scope>
<IOProtocol>ap_ctrl_hs</IOProtocol>
<IOConfig></IOConfig>
<Dir>out</Dir>
<Bits>33</Bits>
<Attribute>data</Attribute>
</RtlPorts>
<RtlPorts>
<name>ap_return_5</name>
<Object>layernormalize&lt;ap_fixed&lt;16, 6, 5, 3, 0&gt;, ap_fixed&lt;33, 13, 5, 3, 0&gt;, config2&gt;</Object>
<Type>return value</Type>
<Scope></Scope>
<IOProtocol>ap_ctrl_hs</IOProtocol>
<IOConfig></IOConfig>
<Dir>out</Dir>
<Bits>33</Bits>
<Attribute>data</Attribute>
</RtlPorts>
<RtlPorts>
<name>ap_return_6</name>
<Object>layernormalize&lt;ap_fixed&lt;16, 6, 5, 3, 0&gt;, ap_fixed&lt;33, 13, 5, 3, 0&gt;, config2&gt;</Object>
<Type>return value</Type>
<Scope></Scope>
<IOProtocol>ap_ctrl_hs</IOProtocol>
<IOConfig></IOConfig>
<Dir>out</Dir>
<Bits>33</Bits>
<Attribute>data</Attribute>
</RtlPorts>
<RtlPorts>
<name>ap_return_7</name>
<Object>layernormalize&lt;ap_fixed&lt;16, 6, 5, 3, 0&gt;, ap_fixed&lt;33, 13, 5, 3, 0&gt;, config2&gt;</Object>
<Type>return value</Type>
<Scope></Scope>
<IOProtocol>ap_ctrl_hs</IOProtocol>
<IOConfig></IOConfig>
<Dir>out</Dir>
<Bits>33</Bits>
<Attribute>data</Attribute>
</RtlPorts>
<RtlPorts>
<name>ap_return_8</name>
<Object>layernormalize&lt;ap_fixed&lt;16, 6, 5, 3, 0&gt;, ap_fixed&lt;33, 13, 5, 3, 0&gt;, config2&gt;</Object>
<Type>return value</Type>
<Scope></Scope>
<IOProtocol>ap_ctrl_hs</IOProtocol>
<IOConfig></IOConfig>
<Dir>out</Dir>
<Bits>33</Bits>
<Attribute>data</Attribute>
</RtlPorts>
<RtlPorts>
<name>ap_return_9</name>
<Object>layernormalize&lt;ap_fixed&lt;16, 6, 5, 3, 0&gt;, ap_fixed&lt;33, 13, 5, 3, 0&gt;, config2&gt;</Object>
<Type>return value</Type>
<Scope></Scope>
<IOProtocol>ap_ctrl_hs</IOProtocol>
<IOConfig></IOConfig>
<Dir>out</Dir>
<Bits>33</Bits>
<Attribute>data</Attribute>
</RtlPorts>
<RtlPorts>
<name>ap_return_10</name>
<Object>layernormalize&lt;ap_fixed&lt;16, 6, 5, 3, 0&gt;, ap_fixed&lt;33, 13, 5, 3, 0&gt;, config2&gt;</Object>
<Type>return value</Type>
<Scope></Scope>
<IOProtocol>ap_ctrl_hs</IOProtocol>
<IOConfig></IOConfig>
<Dir>out</Dir>
<Bits>33</Bits>
<Attribute>data</Attribute>
</RtlPorts>
<RtlPorts>
<name>ap_return_11</name>
<Object>layernormalize&lt;ap_fixed&lt;16, 6, 5, 3, 0&gt;, ap_fixed&lt;33, 13, 5, 3, 0&gt;, config2&gt;</Object>
<Type>return value</Type>
<Scope></Scope>
<IOProtocol>ap_ctrl_hs</IOProtocol>
<IOConfig></IOConfig>
<Dir>out</Dir>
<Bits>33</Bits>
<Attribute>data</Attribute>
</RtlPorts>
<RtlPorts>
<name>ap_return_12</name>
<Object>layernormalize&lt;ap_fixed&lt;16, 6, 5, 3, 0&gt;, ap_fixed&lt;33, 13, 5, 3, 0&gt;, config2&gt;</Object>
<Type>return value</Type>
<Scope></Scope>
<IOProtocol>ap_ctrl_hs</IOProtocol>
<IOConfig></IOConfig>
<Dir>out</Dir>
<Bits>33</Bits>
<Attribute>data</Attribute>
</RtlPorts>
<RtlPorts>
<name>ap_return_13</name>
<Object>layernormalize&lt;ap_fixed&lt;16, 6, 5, 3, 0&gt;, ap_fixed&lt;33, 13, 5, 3, 0&gt;, config2&gt;</Object>
<Type>return value</Type>
<Scope></Scope>
<IOProtocol>ap_ctrl_hs</IOProtocol>
<IOConfig></IOConfig>
<Dir>out</Dir>
<Bits>33</Bits>
<Attribute>data</Attribute>
</RtlPorts>
<RtlPorts>
<name>ap_return_14</name>
<Object>layernormalize&lt;ap_fixed&lt;16, 6, 5, 3, 0&gt;, ap_fixed&lt;33, 13, 5, 3, 0&gt;, config2&gt;</Object>
<Type>return value</Type>
<Scope></Scope>
<IOProtocol>ap_ctrl_hs</IOProtocol>
<IOConfig></IOConfig>
<Dir>out</Dir>
<Bits>33</Bits>
<Attribute>data</Attribute>
</RtlPorts>
<RtlPorts>
<name>ap_return_15</name>
<Object>layernormalize&lt;ap_fixed&lt;16, 6, 5, 3, 0&gt;, ap_fixed&lt;33, 13, 5, 3, 0&gt;, config2&gt;</Object>
<Type>return value</Type>
<Scope></Scope>
<IOProtocol>ap_ctrl_hs</IOProtocol>
<IOConfig></IOConfig>
<Dir>out</Dir>
<Bits>33</Bits>
<Attribute>data</Attribute>
</RtlPorts>
<RtlPorts>
<name>ap_return_16</name>
<Object>layernormalize&lt;ap_fixed&lt;16, 6, 5, 3, 0&gt;, ap_fixed&lt;33, 13, 5, 3, 0&gt;, config2&gt;</Object>
<Type>return value</Type>
<Scope></Scope>
<IOProtocol>ap_ctrl_hs</IOProtocol>
<IOConfig></IOConfig>
<Dir>out</Dir>
<Bits>33</Bits>
<Attribute>data</Attribute>
</RtlPorts>
<RtlPorts>
<name>ap_return_17</name>
<Object>layernormalize&lt;ap_fixed&lt;16, 6, 5, 3, 0&gt;, ap_fixed&lt;33, 13, 5, 3, 0&gt;, config2&gt;</Object>
<Type>return value</Type>
<Scope></Scope>
<IOProtocol>ap_ctrl_hs</IOProtocol>
<IOConfig></IOConfig>
<Dir>out</Dir>
<Bits>33</Bits>
<Attribute>data</Attribute>
</RtlPorts>
<RtlPorts>
<name>ap_return_18</name>
<Object>layernormalize&lt;ap_fixed&lt;16, 6, 5, 3, 0&gt;, ap_fixed&lt;33, 13, 5, 3, 0&gt;, config2&gt;</Object>
<Type>return value</Type>
<Scope></Scope>
<IOProtocol>ap_ctrl_hs</IOProtocol>
<IOConfig></IOConfig>
<Dir>out</Dir>
<Bits>33</Bits>
<Attribute>data</Attribute>
</RtlPorts>
<RtlPorts>
<name>ap_return_19</name>
<Object>layernormalize&lt;ap_fixed&lt;16, 6, 5, 3, 0&gt;, ap_fixed&lt;33, 13, 5, 3, 0&gt;, config2&gt;</Object>
<Type>return value</Type>
<Scope></Scope>
<IOProtocol>ap_ctrl_hs</IOProtocol>
<IOConfig></IOConfig>
<Dir>out</Dir>
<Bits>33</Bits>
<Attribute>data</Attribute>
</RtlPorts>
<RtlPorts>
<name>ap_return_20</name>
<Object>layernormalize&lt;ap_fixed&lt;16, 6, 5, 3, 0&gt;, ap_fixed&lt;33, 13, 5, 3, 0&gt;, config2&gt;</Object>
<Type>return value</Type>
<Scope></Scope>
<IOProtocol>ap_ctrl_hs</IOProtocol>
<IOConfig></IOConfig>
<Dir>out</Dir>
<Bits>33</Bits>
<Attribute>data</Attribute>
</RtlPorts>
<RtlPorts>
<name>ap_return_21</name>
<Object>layernormalize&lt;ap_fixed&lt;16, 6, 5, 3, 0&gt;, ap_fixed&lt;33, 13, 5, 3, 0&gt;, config2&gt;</Object>
<Type>return value</Type>
<Scope></Scope>
<IOProtocol>ap_ctrl_hs</IOProtocol>
<IOConfig></IOConfig>
<Dir>out</Dir>
<Bits>33</Bits>
<Attribute>data</Attribute>
</RtlPorts>
<RtlPorts>
<name>ap_return_22</name>
<Object>layernormalize&lt;ap_fixed&lt;16, 6, 5, 3, 0&gt;, ap_fixed&lt;33, 13, 5, 3, 0&gt;, config2&gt;</Object>
<Type>return value</Type>
<Scope></Scope>
<IOProtocol>ap_ctrl_hs</IOProtocol>
<IOConfig></IOConfig>
<Dir>out</Dir>
<Bits>33</Bits>
<Attribute>data</Attribute>
</RtlPorts>
<RtlPorts>
<name>ap_return_23</name>
<Object>layernormalize&lt;ap_fixed&lt;16, 6, 5, 3, 0&gt;, ap_fixed&lt;33, 13, 5, 3, 0&gt;, config2&gt;</Object>
<Type>return value</Type>
<Scope></Scope>
<IOProtocol>ap_ctrl_hs</IOProtocol>
<IOConfig></IOConfig>
<Dir>out</Dir>
<Bits>33</Bits>
<Attribute>data</Attribute>
</RtlPorts>
<RtlPorts>
<name>ap_return_24</name>
<Object>layernormalize&lt;ap_fixed&lt;16, 6, 5, 3, 0&gt;, ap_fixed&lt;33, 13, 5, 3, 0&gt;, config2&gt;</Object>
<Type>return value</Type>
<Scope></Scope>
<IOProtocol>ap_ctrl_hs</IOProtocol>
<IOConfig></IOConfig>
<Dir>out</Dir>
<Bits>33</Bits>
<Attribute>data</Attribute>
</RtlPorts>
<RtlPorts>
<name>ap_return_25</name>
<Object>layernormalize&lt;ap_fixed&lt;16, 6, 5, 3, 0&gt;, ap_fixed&lt;33, 13, 5, 3, 0&gt;, config2&gt;</Object>
<Type>return value</Type>
<Scope></Scope>
<IOProtocol>ap_ctrl_hs</IOProtocol>
<IOConfig></IOConfig>
<Dir>out</Dir>
<Bits>33</Bits>
<Attribute>data</Attribute>
</RtlPorts>
<RtlPorts>
<name>ap_return_26</name>
<Object>layernormalize&lt;ap_fixed&lt;16, 6, 5, 3, 0&gt;, ap_fixed&lt;33, 13, 5, 3, 0&gt;, config2&gt;</Object>
<Type>return value</Type>
<Scope></Scope>
<IOProtocol>ap_ctrl_hs</IOProtocol>
<IOConfig></IOConfig>
<Dir>out</Dir>
<Bits>33</Bits>
<Attribute>data</Attribute>
</RtlPorts>
<RtlPorts>
<name>ap_return_27</name>
<Object>layernormalize&lt;ap_fixed&lt;16, 6, 5, 3, 0&gt;, ap_fixed&lt;33, 13, 5, 3, 0&gt;, config2&gt;</Object>
<Type>return value</Type>
<Scope></Scope>
<IOProtocol>ap_ctrl_hs</IOProtocol>
<IOConfig></IOConfig>
<Dir>out</Dir>
<Bits>33</Bits>
<Attribute>data</Attribute>
</RtlPorts>
<RtlPorts>
<name>ap_return_28</name>
<Object>layernormalize&lt;ap_fixed&lt;16, 6, 5, 3, 0&gt;, ap_fixed&lt;33, 13, 5, 3, 0&gt;, config2&gt;</Object>
<Type>return value</Type>
<Scope></Scope>
<IOProtocol>ap_ctrl_hs</IOProtocol>
<IOConfig></IOConfig>
<Dir>out</Dir>
<Bits>33</Bits>
<Attribute>data</Attribute>
</RtlPorts>
<RtlPorts>
<name>ap_return_29</name>
<Object>layernormalize&lt;ap_fixed&lt;16, 6, 5, 3, 0&gt;, ap_fixed&lt;33, 13, 5, 3, 0&gt;, config2&gt;</Object>
<Type>return value</Type>
<Scope></Scope>
<IOProtocol>ap_ctrl_hs</IOProtocol>
<IOConfig></IOConfig>
<Dir>out</Dir>
<Bits>33</Bits>
<Attribute>data</Attribute>
</RtlPorts>
<RtlPorts>
<name>ap_return_30</name>
<Object>layernormalize&lt;ap_fixed&lt;16, 6, 5, 3, 0&gt;, ap_fixed&lt;33, 13, 5, 3, 0&gt;, config2&gt;</Object>
<Type>return value</Type>
<Scope></Scope>
<IOProtocol>ap_ctrl_hs</IOProtocol>
<IOConfig></IOConfig>
<Dir>out</Dir>
<Bits>33</Bits>
<Attribute>data</Attribute>
</RtlPorts>
<RtlPorts>
<name>ap_return_31</name>
<Object>layernormalize&lt;ap_fixed&lt;16, 6, 5, 3, 0&gt;, ap_fixed&lt;33, 13, 5, 3, 0&gt;, config2&gt;</Object>
<Type>return value</Type>
<Scope></Scope>
<IOProtocol>ap_ctrl_hs</IOProtocol>
<IOConfig></IOConfig>
<Dir>out</Dir>
<Bits>33</Bits>
<Attribute>data</Attribute>
</RtlPorts>
<RtlPorts>
<name>ap_return_32</name>
<Object>layernormalize&lt;ap_fixed&lt;16, 6, 5, 3, 0&gt;, ap_fixed&lt;33, 13, 5, 3, 0&gt;, config2&gt;</Object>
<Type>return value</Type>
<Scope></Scope>
<IOProtocol>ap_ctrl_hs</IOProtocol>
<IOConfig></IOConfig>
<Dir>out</Dir>
<Bits>33</Bits>
<Attribute>data</Attribute>
</RtlPorts>
<RtlPorts>
<name>ap_return_33</name>
<Object>layernormalize&lt;ap_fixed&lt;16, 6, 5, 3, 0&gt;, ap_fixed&lt;33, 13, 5, 3, 0&gt;, config2&gt;</Object>
<Type>return value</Type>
<Scope></Scope>
<IOProtocol>ap_ctrl_hs</IOProtocol>
<IOConfig></IOConfig>
<Dir>out</Dir>
<Bits>33</Bits>
<Attribute>data</Attribute>
</RtlPorts>
<RtlPorts>
<name>ap_return_34</name>
<Object>layernormalize&lt;ap_fixed&lt;16, 6, 5, 3, 0&gt;, ap_fixed&lt;33, 13, 5, 3, 0&gt;, config2&gt;</Object>
<Type>return value</Type>
<Scope></Scope>
<IOProtocol>ap_ctrl_hs</IOProtocol>
<IOConfig></IOConfig>
<Dir>out</Dir>
<Bits>33</Bits>
<Attribute>data</Attribute>
</RtlPorts>
<RtlPorts>
<name>ap_return_35</name>
<Object>layernormalize&lt;ap_fixed&lt;16, 6, 5, 3, 0&gt;, ap_fixed&lt;33, 13, 5, 3, 0&gt;, config2&gt;</Object>
<Type>return value</Type>
<Scope></Scope>
<IOProtocol>ap_ctrl_hs</IOProtocol>
<IOConfig></IOConfig>
<Dir>out</Dir>
<Bits>33</Bits>
<Attribute>data</Attribute>
</RtlPorts>
<RtlPorts>
<name>ap_return_36</name>
<Object>layernormalize&lt;ap_fixed&lt;16, 6, 5, 3, 0&gt;, ap_fixed&lt;33, 13, 5, 3, 0&gt;, config2&gt;</Object>
<Type>return value</Type>
<Scope></Scope>
<IOProtocol>ap_ctrl_hs</IOProtocol>
<IOConfig></IOConfig>
<Dir>out</Dir>
<Bits>33</Bits>
<Attribute>data</Attribute>
</RtlPorts>
<RtlPorts>
<name>ap_return_37</name>
<Object>layernormalize&lt;ap_fixed&lt;16, 6, 5, 3, 0&gt;, ap_fixed&lt;33, 13, 5, 3, 0&gt;, config2&gt;</Object>
<Type>return value</Type>
<Scope></Scope>
<IOProtocol>ap_ctrl_hs</IOProtocol>
<IOConfig></IOConfig>
<Dir>out</Dir>
<Bits>33</Bits>
<Attribute>data</Attribute>
</RtlPorts>
<RtlPorts>
<name>ap_return_38</name>
<Object>layernormalize&lt;ap_fixed&lt;16, 6, 5, 3, 0&gt;, ap_fixed&lt;33, 13, 5, 3, 0&gt;, config2&gt;</Object>
<Type>return value</Type>
<Scope></Scope>
<IOProtocol>ap_ctrl_hs</IOProtocol>
<IOConfig></IOConfig>
<Dir>out</Dir>
<Bits>33</Bits>
<Attribute>data</Attribute>
</RtlPorts>
<RtlPorts>
<name>ap_return_39</name>
<Object>layernormalize&lt;ap_fixed&lt;16, 6, 5, 3, 0&gt;, ap_fixed&lt;33, 13, 5, 3, 0&gt;, config2&gt;</Object>
<Type>return value</Type>
<Scope></Scope>
<IOProtocol>ap_ctrl_hs</IOProtocol>
<IOConfig></IOConfig>
<Dir>out</Dir>
<Bits>33</Bits>
<Attribute>data</Attribute>
</RtlPorts>
<RtlPorts>
<name>ap_return_40</name>
<Object>layernormalize&lt;ap_fixed&lt;16, 6, 5, 3, 0&gt;, ap_fixed&lt;33, 13, 5, 3, 0&gt;, config2&gt;</Object>
<Type>return value</Type>
<Scope></Scope>
<IOProtocol>ap_ctrl_hs</IOProtocol>
<IOConfig></IOConfig>
<Dir>out</Dir>
<Bits>33</Bits>
<Attribute>data</Attribute>
</RtlPorts>
<RtlPorts>
<name>ap_return_41</name>
<Object>layernormalize&lt;ap_fixed&lt;16, 6, 5, 3, 0&gt;, ap_fixed&lt;33, 13, 5, 3, 0&gt;, config2&gt;</Object>
<Type>return value</Type>
<Scope></Scope>
<IOProtocol>ap_ctrl_hs</IOProtocol>
<IOConfig></IOConfig>
<Dir>out</Dir>
<Bits>33</Bits>
<Attribute>data</Attribute>
</RtlPorts>
<RtlPorts>
<name>ap_return_42</name>
<Object>layernormalize&lt;ap_fixed&lt;16, 6, 5, 3, 0&gt;, ap_fixed&lt;33, 13, 5, 3, 0&gt;, config2&gt;</Object>
<Type>return value</Type>
<Scope></Scope>
<IOProtocol>ap_ctrl_hs</IOProtocol>
<IOConfig></IOConfig>
<Dir>out</Dir>
<Bits>33</Bits>
<Attribute>data</Attribute>
</RtlPorts>
<RtlPorts>
<name>ap_return_43</name>
<Object>layernormalize&lt;ap_fixed&lt;16, 6, 5, 3, 0&gt;, ap_fixed&lt;33, 13, 5, 3, 0&gt;, config2&gt;</Object>
<Type>return value</Type>
<Scope></Scope>
<IOProtocol>ap_ctrl_hs</IOProtocol>
<IOConfig></IOConfig>
<Dir>out</Dir>
<Bits>33</Bits>
<Attribute>data</Attribute>
</RtlPorts>
<RtlPorts>
<name>ap_return_44</name>
<Object>layernormalize&lt;ap_fixed&lt;16, 6, 5, 3, 0&gt;, ap_fixed&lt;33, 13, 5, 3, 0&gt;, config2&gt;</Object>
<Type>return value</Type>
<Scope></Scope>
<IOProtocol>ap_ctrl_hs</IOProtocol>
<IOConfig></IOConfig>
<Dir>out</Dir>
<Bits>33</Bits>
<Attribute>data</Attribute>
</RtlPorts>
<RtlPorts>
<name>ap_return_45</name>
<Object>layernormalize&lt;ap_fixed&lt;16, 6, 5, 3, 0&gt;, ap_fixed&lt;33, 13, 5, 3, 0&gt;, config2&gt;</Object>
<Type>return value</Type>
<Scope></Scope>
<IOProtocol>ap_ctrl_hs</IOProtocol>
<IOConfig></IOConfig>
<Dir>out</Dir>
<Bits>33</Bits>
<Attribute>data</Attribute>
</RtlPorts>
<RtlPorts>
<name>ap_return_46</name>
<Object>layernormalize&lt;ap_fixed&lt;16, 6, 5, 3, 0&gt;, ap_fixed&lt;33, 13, 5, 3, 0&gt;, config2&gt;</Object>
<Type>return value</Type>
<Scope></Scope>
<IOProtocol>ap_ctrl_hs</IOProtocol>
<IOConfig></IOConfig>
<Dir>out</Dir>
<Bits>33</Bits>
<Attribute>data</Attribute>
</RtlPorts>
<RtlPorts>
<name>ap_return_47</name>
<Object>layernormalize&lt;ap_fixed&lt;16, 6, 5, 3, 0&gt;, ap_fixed&lt;33, 13, 5, 3, 0&gt;, config2&gt;</Object>
<Type>return value</Type>
<Scope></Scope>
<IOProtocol>ap_ctrl_hs</IOProtocol>
<IOConfig></IOConfig>
<Dir>out</Dir>
<Bits>33</Bits>
<Attribute>data</Attribute>
</RtlPorts>
<RtlPorts>
<name>ap_return_48</name>
<Object>layernormalize&lt;ap_fixed&lt;16, 6, 5, 3, 0&gt;, ap_fixed&lt;33, 13, 5, 3, 0&gt;, config2&gt;</Object>
<Type>return value</Type>
<Scope></Scope>
<IOProtocol>ap_ctrl_hs</IOProtocol>
<IOConfig></IOConfig>
<Dir>out</Dir>
<Bits>33</Bits>
<Attribute>data</Attribute>
</RtlPorts>
<RtlPorts>
<name>ap_return_49</name>
<Object>layernormalize&lt;ap_fixed&lt;16, 6, 5, 3, 0&gt;, ap_fixed&lt;33, 13, 5, 3, 0&gt;, config2&gt;</Object>
<Type>return value</Type>
<Scope></Scope>
<IOProtocol>ap_ctrl_hs</IOProtocol>
<IOConfig></IOConfig>
<Dir>out</Dir>
<Bits>33</Bits>
<Attribute>data</Attribute>
</RtlPorts>
<RtlPorts>
<name>ap_return_50</name>
<Object>layernormalize&lt;ap_fixed&lt;16, 6, 5, 3, 0&gt;, ap_fixed&lt;33, 13, 5, 3, 0&gt;, config2&gt;</Object>
<Type>return value</Type>
<Scope></Scope>
<IOProtocol>ap_ctrl_hs</IOProtocol>
<IOConfig></IOConfig>
<Dir>out</Dir>
<Bits>33</Bits>
<Attribute>data</Attribute>
</RtlPorts>
<RtlPorts>
<name>ap_return_51</name>
<Object>layernormalize&lt;ap_fixed&lt;16, 6, 5, 3, 0&gt;, ap_fixed&lt;33, 13, 5, 3, 0&gt;, config2&gt;</Object>
<Type>return value</Type>
<Scope></Scope>
<IOProtocol>ap_ctrl_hs</IOProtocol>
<IOConfig></IOConfig>
<Dir>out</Dir>
<Bits>33</Bits>
<Attribute>data</Attribute>
</RtlPorts>
<RtlPorts>
<name>ap_return_52</name>
<Object>layernormalize&lt;ap_fixed&lt;16, 6, 5, 3, 0&gt;, ap_fixed&lt;33, 13, 5, 3, 0&gt;, config2&gt;</Object>
<Type>return value</Type>
<Scope></Scope>
<IOProtocol>ap_ctrl_hs</IOProtocol>
<IOConfig></IOConfig>
<Dir>out</Dir>
<Bits>33</Bits>
<Attribute>data</Attribute>
</RtlPorts>
<RtlPorts>
<name>ap_return_53</name>
<Object>layernormalize&lt;ap_fixed&lt;16, 6, 5, 3, 0&gt;, ap_fixed&lt;33, 13, 5, 3, 0&gt;, config2&gt;</Object>
<Type>return value</Type>
<Scope></Scope>
<IOProtocol>ap_ctrl_hs</IOProtocol>
<IOConfig></IOConfig>
<Dir>out</Dir>
<Bits>33</Bits>
<Attribute>data</Attribute>
</RtlPorts>
<RtlPorts>
<name>ap_return_54</name>
<Object>layernormalize&lt;ap_fixed&lt;16, 6, 5, 3, 0&gt;, ap_fixed&lt;33, 13, 5, 3, 0&gt;, config2&gt;</Object>
<Type>return value</Type>
<Scope></Scope>
<IOProtocol>ap_ctrl_hs</IOProtocol>
<IOConfig></IOConfig>
<Dir>out</Dir>
<Bits>33</Bits>
<Attribute>data</Attribute>
</RtlPorts>
<RtlPorts>
<name>ap_return_55</name>
<Object>layernormalize&lt;ap_fixed&lt;16, 6, 5, 3, 0&gt;, ap_fixed&lt;33, 13, 5, 3, 0&gt;, config2&gt;</Object>
<Type>return value</Type>
<Scope></Scope>
<IOProtocol>ap_ctrl_hs</IOProtocol>
<IOConfig></IOConfig>
<Dir>out</Dir>
<Bits>33</Bits>
<Attribute>data</Attribute>
</RtlPorts>
<RtlPorts>
<name>ap_return_56</name>
<Object>layernormalize&lt;ap_fixed&lt;16, 6, 5, 3, 0&gt;, ap_fixed&lt;33, 13, 5, 3, 0&gt;, config2&gt;</Object>
<Type>return value</Type>
<Scope></Scope>
<IOProtocol>ap_ctrl_hs</IOProtocol>
<IOConfig></IOConfig>
<Dir>out</Dir>
<Bits>33</Bits>
<Attribute>data</Attribute>
</RtlPorts>
<RtlPorts>
<name>ap_return_57</name>
<Object>layernormalize&lt;ap_fixed&lt;16, 6, 5, 3, 0&gt;, ap_fixed&lt;33, 13, 5, 3, 0&gt;, config2&gt;</Object>
<Type>return value</Type>
<Scope></Scope>
<IOProtocol>ap_ctrl_hs</IOProtocol>
<IOConfig></IOConfig>
<Dir>out</Dir>
<Bits>33</Bits>
<Attribute>data</Attribute>
</RtlPorts>
<RtlPorts>
<name>ap_return_58</name>
<Object>layernormalize&lt;ap_fixed&lt;16, 6, 5, 3, 0&gt;, ap_fixed&lt;33, 13, 5, 3, 0&gt;, config2&gt;</Object>
<Type>return value</Type>
<Scope></Scope>
<IOProtocol>ap_ctrl_hs</IOProtocol>
<IOConfig></IOConfig>
<Dir>out</Dir>
<Bits>33</Bits>
<Attribute>data</Attribute>
</RtlPorts>
<RtlPorts>
<name>ap_return_59</name>
<Object>layernormalize&lt;ap_fixed&lt;16, 6, 5, 3, 0&gt;, ap_fixed&lt;33, 13, 5, 3, 0&gt;, config2&gt;</Object>
<Type>return value</Type>
<Scope></Scope>
<IOProtocol>ap_ctrl_hs</IOProtocol>
<IOConfig></IOConfig>
<Dir>out</Dir>
<Bits>33</Bits>
<Attribute>data</Attribute>
</RtlPorts>
<RtlPorts>
<name>ap_return_60</name>
<Object>layernormalize&lt;ap_fixed&lt;16, 6, 5, 3, 0&gt;, ap_fixed&lt;33, 13, 5, 3, 0&gt;, config2&gt;</Object>
<Type>return value</Type>
<Scope></Scope>
<IOProtocol>ap_ctrl_hs</IOProtocol>
<IOConfig></IOConfig>
<Dir>out</Dir>
<Bits>33</Bits>
<Attribute>data</Attribute>
</RtlPorts>
<RtlPorts>
<name>ap_return_61</name>
<Object>layernormalize&lt;ap_fixed&lt;16, 6, 5, 3, 0&gt;, ap_fixed&lt;33, 13, 5, 3, 0&gt;, config2&gt;</Object>
<Type>return value</Type>
<Scope></Scope>
<IOProtocol>ap_ctrl_hs</IOProtocol>
<IOConfig></IOConfig>
<Dir>out</Dir>
<Bits>33</Bits>
<Attribute>data</Attribute>
</RtlPorts>
<RtlPorts>
<name>ap_return_62</name>
<Object>layernormalize&lt;ap_fixed&lt;16, 6, 5, 3, 0&gt;, ap_fixed&lt;33, 13, 5, 3, 0&gt;, config2&gt;</Object>
<Type>return value</Type>
<Scope></Scope>
<IOProtocol>ap_ctrl_hs</IOProtocol>
<IOConfig></IOConfig>
<Dir>out</Dir>
<Bits>33</Bits>
<Attribute>data</Attribute>
</RtlPorts>
<RtlPorts>
<name>ap_return_63</name>
<Object>layernormalize&lt;ap_fixed&lt;16, 6, 5, 3, 0&gt;, ap_fixed&lt;33, 13, 5, 3, 0&gt;, config2&gt;</Object>
<Type>return value</Type>
<Scope></Scope>
<IOProtocol>ap_ctrl_hs</IOProtocol>
<IOConfig></IOConfig>
<Dir>out</Dir>
<Bits>33</Bits>
<Attribute>data</Attribute>
</RtlPorts>
<RtlPorts>
<name>ap_return_64</name>
<Object>layernormalize&lt;ap_fixed&lt;16, 6, 5, 3, 0&gt;, ap_fixed&lt;33, 13, 5, 3, 0&gt;, config2&gt;</Object>
<Type>return value</Type>
<Scope></Scope>
<IOProtocol>ap_ctrl_hs</IOProtocol>
<IOConfig></IOConfig>
<Dir>out</Dir>
<Bits>33</Bits>
<Attribute>data</Attribute>
</RtlPorts>
<RtlPorts>
<name>ap_return_65</name>
<Object>layernormalize&lt;ap_fixed&lt;16, 6, 5, 3, 0&gt;, ap_fixed&lt;33, 13, 5, 3, 0&gt;, config2&gt;</Object>
<Type>return value</Type>
<Scope></Scope>
<IOProtocol>ap_ctrl_hs</IOProtocol>
<IOConfig></IOConfig>
<Dir>out</Dir>
<Bits>33</Bits>
<Attribute>data</Attribute>
</RtlPorts>
<RtlPorts>
<name>ap_return_66</name>
<Object>layernormalize&lt;ap_fixed&lt;16, 6, 5, 3, 0&gt;, ap_fixed&lt;33, 13, 5, 3, 0&gt;, config2&gt;</Object>
<Type>return value</Type>
<Scope></Scope>
<IOProtocol>ap_ctrl_hs</IOProtocol>
<IOConfig></IOConfig>
<Dir>out</Dir>
<Bits>33</Bits>
<Attribute>data</Attribute>
</RtlPorts>
<RtlPorts>
<name>ap_return_67</name>
<Object>layernormalize&lt;ap_fixed&lt;16, 6, 5, 3, 0&gt;, ap_fixed&lt;33, 13, 5, 3, 0&gt;, config2&gt;</Object>
<Type>return value</Type>
<Scope></Scope>
<IOProtocol>ap_ctrl_hs</IOProtocol>
<IOConfig></IOConfig>
<Dir>out</Dir>
<Bits>33</Bits>
<Attribute>data</Attribute>
</RtlPorts>
<RtlPorts>
<name>ap_return_68</name>
<Object>layernormalize&lt;ap_fixed&lt;16, 6, 5, 3, 0&gt;, ap_fixed&lt;33, 13, 5, 3, 0&gt;, config2&gt;</Object>
<Type>return value</Type>
<Scope></Scope>
<IOProtocol>ap_ctrl_hs</IOProtocol>
<IOConfig></IOConfig>
<Dir>out</Dir>
<Bits>33</Bits>
<Attribute>data</Attribute>
</RtlPorts>
<RtlPorts>
<name>ap_return_69</name>
<Object>layernormalize&lt;ap_fixed&lt;16, 6, 5, 3, 0&gt;, ap_fixed&lt;33, 13, 5, 3, 0&gt;, config2&gt;</Object>
<Type>return value</Type>
<Scope></Scope>
<IOProtocol>ap_ctrl_hs</IOProtocol>
<IOConfig></IOConfig>
<Dir>out</Dir>
<Bits>33</Bits>
<Attribute>data</Attribute>
</RtlPorts>
<RtlPorts>
<name>ap_return_70</name>
<Object>layernormalize&lt;ap_fixed&lt;16, 6, 5, 3, 0&gt;, ap_fixed&lt;33, 13, 5, 3, 0&gt;, config2&gt;</Object>
<Type>return value</Type>
<Scope></Scope>
<IOProtocol>ap_ctrl_hs</IOProtocol>
<IOConfig></IOConfig>
<Dir>out</Dir>
<Bits>33</Bits>
<Attribute>data</Attribute>
</RtlPorts>
<RtlPorts>
<name>ap_return_71</name>
<Object>layernormalize&lt;ap_fixed&lt;16, 6, 5, 3, 0&gt;, ap_fixed&lt;33, 13, 5, 3, 0&gt;, config2&gt;</Object>
<Type>return value</Type>
<Scope></Scope>
<IOProtocol>ap_ctrl_hs</IOProtocol>
<IOConfig></IOConfig>
<Dir>out</Dir>
<Bits>33</Bits>
<Attribute>data</Attribute>
</RtlPorts>
<RtlPorts>
<name>ap_return_72</name>
<Object>layernormalize&lt;ap_fixed&lt;16, 6, 5, 3, 0&gt;, ap_fixed&lt;33, 13, 5, 3, 0&gt;, config2&gt;</Object>
<Type>return value</Type>
<Scope></Scope>
<IOProtocol>ap_ctrl_hs</IOProtocol>
<IOConfig></IOConfig>
<Dir>out</Dir>
<Bits>33</Bits>
<Attribute>data</Attribute>
</RtlPorts>
<RtlPorts>
<name>ap_return_73</name>
<Object>layernormalize&lt;ap_fixed&lt;16, 6, 5, 3, 0&gt;, ap_fixed&lt;33, 13, 5, 3, 0&gt;, config2&gt;</Object>
<Type>return value</Type>
<Scope></Scope>
<IOProtocol>ap_ctrl_hs</IOProtocol>
<IOConfig></IOConfig>
<Dir>out</Dir>
<Bits>33</Bits>
<Attribute>data</Attribute>
</RtlPorts>
<RtlPorts>
<name>ap_return_74</name>
<Object>layernormalize&lt;ap_fixed&lt;16, 6, 5, 3, 0&gt;, ap_fixed&lt;33, 13, 5, 3, 0&gt;, config2&gt;</Object>
<Type>return value</Type>
<Scope></Scope>
<IOProtocol>ap_ctrl_hs</IOProtocol>
<IOConfig></IOConfig>
<Dir>out</Dir>
<Bits>33</Bits>
<Attribute>data</Attribute>
</RtlPorts>
<RtlPorts>
<name>ap_return_75</name>
<Object>layernormalize&lt;ap_fixed&lt;16, 6, 5, 3, 0&gt;, ap_fixed&lt;33, 13, 5, 3, 0&gt;, config2&gt;</Object>
<Type>return value</Type>
<Scope></Scope>
<IOProtocol>ap_ctrl_hs</IOProtocol>
<IOConfig></IOConfig>
<Dir>out</Dir>
<Bits>33</Bits>
<Attribute>data</Attribute>
</RtlPorts>
<RtlPorts>
<name>ap_return_76</name>
<Object>layernormalize&lt;ap_fixed&lt;16, 6, 5, 3, 0&gt;, ap_fixed&lt;33, 13, 5, 3, 0&gt;, config2&gt;</Object>
<Type>return value</Type>
<Scope></Scope>
<IOProtocol>ap_ctrl_hs</IOProtocol>
<IOConfig></IOConfig>
<Dir>out</Dir>
<Bits>33</Bits>
<Attribute>data</Attribute>
</RtlPorts>
<RtlPorts>
<name>ap_return_77</name>
<Object>layernormalize&lt;ap_fixed&lt;16, 6, 5, 3, 0&gt;, ap_fixed&lt;33, 13, 5, 3, 0&gt;, config2&gt;</Object>
<Type>return value</Type>
<Scope></Scope>
<IOProtocol>ap_ctrl_hs</IOProtocol>
<IOConfig></IOConfig>
<Dir>out</Dir>
<Bits>33</Bits>
<Attribute>data</Attribute>
</RtlPorts>
<RtlPorts>
<name>ap_return_78</name>
<Object>layernormalize&lt;ap_fixed&lt;16, 6, 5, 3, 0&gt;, ap_fixed&lt;33, 13, 5, 3, 0&gt;, config2&gt;</Object>
<Type>return value</Type>
<Scope></Scope>
<IOProtocol>ap_ctrl_hs</IOProtocol>
<IOConfig></IOConfig>
<Dir>out</Dir>
<Bits>33</Bits>
<Attribute>data</Attribute>
</RtlPorts>
<RtlPorts>
<name>ap_return_79</name>
<Object>layernormalize&lt;ap_fixed&lt;16, 6, 5, 3, 0&gt;, ap_fixed&lt;33, 13, 5, 3, 0&gt;, config2&gt;</Object>
<Type>return value</Type>
<Scope></Scope>
<IOProtocol>ap_ctrl_hs</IOProtocol>
<IOConfig></IOConfig>
<Dir>out</Dir>
<Bits>33</Bits>
<Attribute>data</Attribute>
</RtlPorts>
<RtlPorts>
<name>data_val</name>
<Object>data_val</Object>
<Type>scalar</Type>
<Scope></Scope>
<IOProtocol>ap_none</IOProtocol>
<IOConfig></IOConfig>
<Dir>in</Dir>
<Bits>1280</Bits>
<Attribute>data</Attribute>
</RtlPorts>
</InterfaceSummary>

</profile>
