{
  "0": {
    "basicblocks": 1,
    "calls": "4 2 3",
    "file": "myproject.cpp",
    "fileloc": 7,
    "instructions": 16,
    "name": "myproject",
    "total_instructions": 96800
  },
  "1": {
    "basicblocks": 1340,
    "calls": "",
    "file": "nnet_layernorm.h",
    "fileloc": 46,
    "instructions": 2965,
    "loads": {
      "G": 1,
      "L": 144
    },
    "name": "layernorm_1d<ap_fixed<16, 6, AP_TRN, AP_WRAP, 0>, ap_fixed<33, 13, AP_TRN, AP_WRAP, 0>, config2>",
    "stores": {
      "L": 32
    },
    "total_instructions": 2965
  },
  "2": {
    "basicblocks": 20,
    "calls": "",
    "file": "nnet_array.h",
    "fileloc": 16,
    "instructions": 1938,
    "loads": {
      "L": 480
    },
    "name": "transpose_2d<ap_fixed<16, 6, AP_TRN, AP_WRAP, 0>, ap_fixed<16, 6, AP_TRN, AP_WRAP, 0>, config4>",
    "stores": {
      "L": 480
    },
    "total_instructions": 1938
  },
  "3": {
    "basicblocks": 64,
    "calls": "1 1 1 1 1 1 1 1 1 1 1 1 1 1 1 1 1 1 1 1 1 1 1 1 1 1 1 1 1 1",
    "file": "nnet_layernorm.h",
    "fileloc": 104,
    "instructions": 3944,
    "loads": {
      "L": 960
    },
    "name": "layernormalize<ap_fixed<16, 6, AP_TRN, AP_WRAP, 0>, ap_fixed<33, 13, AP_TRN, AP_WRAP, 0>, config2>",
    "stores": {
      "L": 960
    },
    "total_instructions": 92894
  },
  "4": {
    "basicblocks": 34,
    "calls": "",
    "file": "nnet_array.h",
    "fileloc": 16,
    "instructions": 1952,
    "loads": {
      "L": 480
    },
    "name": "transpose_2d<ap_fixed<16, 6, AP_TRN, AP_WRAP, 0>, ap_fixed<16, 6, AP_TRN, AP_WRAP, 0>, config3>",
    "stores": {
      "L": 480
    },
    "total_instructions": 1952
  }
}