{
  "0": {
    "basicblocks": 1,
    "calls": "1",
    "file": "myproject.cpp",
    "fileloc": 7,
    "instructions": 84,
    "loads": {
      "T": 1
    },
    "name": "myproject",
    "total_instructions": 13943
  },
  "1": {
    "basicblocks": 1,
    "calls": "2 2 2 2 2 2 2 2 2 2",
    "file": "nnet_layernorm.h",
    "fileloc": 107,
    "instructions": 259,
    "loads": {
      "L": 80
    },
    "name": "layernormalize<ap_fixed<16, 6, AP_TRN, AP_WRAP, 0>, ap_fixed<33, 13, AP_TRN, AP_WRAP, 0>, config2>",
    "stores": {
      "L": 80
    },
    "total_instructions": 13859
  },
  "2": {
    "basicblocks": 24,
    "calls": "",
    "file": "nnet_layernorm.h",
    "fileloc": 49,
    "instructions": 1360,
    "loads": {
      "G": 1
    },
    "name": "layernorm_1d<ap_fixed<16, 6, AP_TRN, AP_WRAP, 0>, ap_fixed<33, 13, AP_TRN, AP_WRAP, 0>, config2>",
    "stores": {
      "L": 8
    },
    "total_instructions": 1360
  }
}